Workbook

Sheet README
A1: Golden Data Set: Agentic Rule Generation for Cloud Security (Case 14, CloudGuard Labs)
A3: Purpose
A4: Ground-truth data used to design and evaluate the AI rule-generation pipeline: (1) offline evaluation before launch, (2) regression test whenever the model or prompts change, (3) go/no-go gate for the MVP.
A6: Where the data comes from (all real, nothing synthetic)
A7: - CIS Amazon Web Services Foundations Benchmark v7.0.0 and v6.0.0: recommendation IDs, titles, section, profile level, assessment status, as mapped in Prowler's compliance files.
A8: - Prowler open-source CSPM (Apache-2.0): check metadata (severity, risk, remediation, Terraform/CLI fixes) and the check source code. The PASS/FAIL messages were extracted directly from each check's Python code.
A9: - AWS What's New RSS feed: the 100 most recent real announcements (14-26 Oct 2026) for the triage set.
A11: Sheets
A12: Positive_Set: one row per (CIS recommendation x reference check) pair. 'What a correct rule looks like' = expected rule output.
A13: Edge_Cases: cases found in the real data that a naive generator gets wrong (one-to-many mappings, shared checks, manual-only controls, no-automation controls, account-vs-resource scope).
A14: Triage_Set: real AWS announcements with an expected triage label: does this need a new rule, an update to an existing rule, or no rule?
A15: Version_Drift: real changes between CIS v6.0 and v7.0. Tests the maintenance agent: which existing rules must be added, retired, re-numbered or re-mapped.
... A27: Key derived facts for the deck
A28: CIS v7.0 recommendations | B28: 70 | C28: in Prowler's CIS v7.0 AWS mapping (counted in build script)
A29: Positive_Set rows | B29: =COUNTA(Positive_Set!A2:A87) -> 86 | C29: recommendation x reference-check pairs
A30: Distinct reference checks | B30: 82 | C30: distinct Prowler checks mapped to CIS v7.0 (counted in build script)
A31: Edge cases | B31: =COUNTA(Edge_Cases!A2:A52) -> 51
A32: Triage announcements | B32: =COUNTA(Triage_Set!A2:A101) -> 100 | C32: real AWS announcements, 14-26 Oct 2026
A33: ...of which need a rule (draft label) | B33: =COUNTIF(Triage_Set!F2:F101,"Y") -> 11 | C33: the rest are noise the Watcher agent must filter out
A34: Version drift items (CIS 6.0 -> 7.0) | B34: =COUNTA(Version_Drift!A2:A32) -> 31
A35: Critical/High severity rows | B35: =COUNTIF(Positive_Set!L2:L87,"critical")+COUNTIF(Positive_Set!L2:L87,"high") -> 37
A36: Rows in tier T3 (mandatory 2-SME sign-off) | B36: =COUNTIF(Positive_Set!T2:T87,"T3") -> 26

Sheet Positive_Set
A1: GS_ID | B1: CIS_ID | C1: CIS_Recommendation | D1: CIS_Section | E1: CIS_Profile | F1: CIS_Assessment | G1: Expected_Check_ID | H1: Check_Title | I1: Service | J1: Resource_Type | K1: Resource_Group | L1: Expected_Severity | M1: Risk (Prowler) | N1: Expected_FAIL_message | O1: Expected_PASS_message | P1: Compliant_Fixture (Terraform) | Q1: Remediation_CLI | R1: AWS_Docs_URLs | S1: Reference_Rule_Code_URL | T1: Proposed_Risk_Tier
A2: P-001 | B2: 2.1.1 | C2: Ensure centralized root access in AWS Organizations | D2: 2 Identity and Access Management | E2: Level 2 | F2: Manual | G2: iam_root_credentials_management_enabled | H2: AWS Organization has centralized root credentials management enabled | I2: iam | J2: Other | K2: IAM | L2: high | M2: Without central control, member accounts can retain or recover long-term root credentials, weakening confidentiality and integrity. Threats include: - Account takeover via root email recovery - Persistent access through root keys - Unfixable lockouts from misconfigured policies - Bypass of separation of duties | N2: Root credentials management is not enabled. | O2: Root credentials management is enabled. | Q2: aws iam enable-organizations-root-credentials-management | R2: https://docs.aws.amazon.com/IAM/latest/UserGuide/id_root-user.html#id_root-user-access-management https://docs.aws.amazon.com/IAM/latest/UserGuide/id_root-enable-root-access.html | S2: https://github.com/prowler-cloud/prowler/blob/master/prowler/providers/aws/services/iam/iam_root_credentials_management_enabled/iam_root_credentials_management_enabled.py | T2: =IF(OR(L2="critical",AND(L2="high",OR(K2="IAM",K2="network"))),"T3",IF(OR(L2="high",L2="medium"),"T2","T1")) -> T3
A3: P-002 | B3: 2.1.5 | C3: Ensure delegated admin manages AWS Organizations policies | D3: 2 Identity and Access Management | E3: Level 2 | F3: Manual | G3: organizations_delegated_administrators | H3: AWS Organization has only trusted delegated administrators | I3: organizations | J3: Other | K3: governance | L3: critical | M3: Unapproved delegated administrators can alter SCPs, invite/move accounts, and create privileged roles, enabling privilege escalation. This undermines guardrails, risking loss of integrity, exposure of confidentiality across accounts, and impacts availability through organization-wide policy changes. | N3: AWS Organization {organizations_client.organization.id} has an untrusted Delegated Administrator: {delegated_administrator.id}. | O3: AWS Organization {organizations_client.organization.id} has a trusted Delegated Administrator: {delegated_administrator.id}. | R3: https://docs.aws.amazon.com/organizations/latest/userguide/orgs_delegate_policies.html | S3: https://github.com/prowler-cloud/prowler/blob/master/prowler/providers/aws/services/organizations/organizations_delegated_administrators/organizations_delegated_administrators.py | T3: =IF(OR(L3="critical",AND(L3="high",OR(K3="IAM",K3="network"))),"T3",IF(OR(L3="high",L3="medium"),"T2","T1")) -> T3
A4: P-003 | B4: 2.1.6 | C4: Ensure delegated admins manage AWS Organizations-integrated services | D4: 2 Identity and Access Management | E4: Level 2 | F4: Manual | G4: organizations_delegated_administrators | H4: AWS Organization has only trusted delegated administrators | I4: organizations | J4: Other | K4: governance | L4: critical | M4: Unapproved delegated administrators can alter SCPs, invite/move accounts, and create privileged roles, enabling privilege escalation. This undermines guardrails, risking loss of integrity, exposure of confidentiality across accounts, and impacts availability through organization-wide policy changes. | N4: AWS Organization {organizations_client.organization.id} has an untrusted Delegated Administrator: {delegated_administrator.id}. | O4: AWS Organization {organizations_client.organization.id} has a trusted Delegated Administrator: {delegated_administrator.id}. | R4: https://docs.aws.amazon.com/organizations/latest/userguide/orgs_delegate_policies.html | S4: https://github.com/prowler-cloud/prowler/blob/master/prowler/providers/aws/services/organizations/organizations_delegated_administrators/organizations_delegated_administrators.py | T4: =IF(OR(L4="critical",AND(L4="high",OR(K4="IAM",K4="network"))),"T3",IF(OR(L4="high",L4="medium"),"T2","T1")) -> T3
A5: P-004 | B5: 2.2 | C5: Maintain current AWS account contact details | D5: 2 Identity and Access Management | E5: Level 1 | F5: Manual | G5: account_maintain_current_contact_details | H5: AWS account contact information is current | I5: account | J5: Other | K5: governance | L5: medium | M5: Outdated or single-person contacts delay security notifications, slow incident response, and complicate account recovery. AWS may throttle services during abuse mitigation, reducing availability. Missed alerts enable ongoing misuse, risking data exfiltration and unauthorized changes (integrity). | P5: # Set the Security alternate contact for the AWS account resource "aws_account_alternate_contact" "<example_resource_name>" { alternate_contact_type = "SECURITY" # Critical: ensures AWS can reach your security team email_address = "<SECURITY_EMAIL>" # Critical: contact destination name = "<SECURITY_CONTACT_NAME>" phone_number = "<SECURITY_PHONE>" title = "Security" } | Q5: aws account put-alternate-contact --alternate-contact-type=SECURITY --email-address=<SECURITY_EMAIL> --name="<SECURITY_CONTACT_NAME>" --phone-number="<SECURITY_PHONE>" --title="Security" | R5: https://docs.aws.amazon.com/security-ir/latest/userguide/update-account-contact-info.html https://docs.aws.amazon.com/accounts/latest/reference/manage-acct-update-contact-primary.html https://aws.amazon.com/blogs/security/update-the-alternate-security-contact-across-your-aws-accounts-for-timely-security-notifications/ https://docs.aws.amazon.com/organizations/latest/userguide/orgs_manage_accounts_update_contacts.html https://docs.aws.amazon.com/accounts/latest/reference/manage-acct-update-contact-alternate.html | S5: https://github.com/prowler-cloud/prowler/blob/master/prowler/providers/aws/services/account/account_maintain_current_contact_details/account_maintain_current_contact_details.py | T5: =IF(OR(L5="critical",AND(L5="high",OR(K5="IAM",K5="network"))),"T3",IF(OR(L5="high",L5="medium"),"T2","T1")) -> T2
A6: P-005 | B6: 2.3 | C6: Ensure security contact information is registered | D6: 2 Identity and Access Management | E6: Level 1 | F6: Manual | G6: account_security_contact_information_is_registered | H6: AWS account has security alternate contact registered | I6: account | J6: Other | K6: governance | L6: medium | M6: Missing or outdated security contact can delay or prevent AWS advisories from reaching responders, increasing risk to: - Confidentiality: data exfiltration from undetected compromise - Integrity: unauthorized changes persist longer - Availability: resource abuse (e.g., cryptomining) and outages | P6: # Set the SECURITY alternate contact for the current AWS account resource "aws_account_alternate_contact" "<example_resource_name>" { alternate_contact_type = "SECURITY" # Critical: sets Security contact type email_address = "security@example.com" # Contact email name = "Security Team" # Contact name phone_number = "+1-555-0100" # Contact phone } | Q6: aws account put-alternate-contact --alternate-contact-type SECURITY --email-address <EMAIL_ADDRESS> --name <CONTACT_NAME> --phone-number <PHONE_NUMBER> | S6: https://github.com/prowler-cloud/prowler/blob/master/prowler/providers/aws/services/account/account_security_contact_information_is_registered/account_security_contact_information_is_registered.py | T6: =IF(OR(L6="critical",AND(L6="high",OR(K6="IAM",K6="network"))),"T3",IF(OR(L6="high",L6="medium"),"T2","T1")) -> T2
A7: P-006 | B7: 2.4 | C7: Ensure no 'root' user account access key exists | D7: 2 Identity and Access Management | E7: Level 1 | F7: Automated | G7: iam_no_root_access_key | H7: Root account has no active access keys | I7: iam | J7: AwsIamAccessKey | K7: IAM | L7: critical | M7: Root access keys provide unrestricted API access. If exposed or misused, attackers can: - Turn off logging and alter policies (integrity) - Read or export data (confidentiality) - Delete resources and lock out admins (availability) Long-lived keys can persist and may bypass console-only MFA. | N7: Root account has two active access keys | O7: Root account has password configured but no access keys. | R7: https://docs.aws.amazon.com/IAM/latest/UserGuide/id_credentials_access-keys.html https://docs.aws.amazon.com/IAM/latest/UserGuide/id_credentials_getting-report.html | S7: https://github.com/prowler-cloud/prowler/blob/master/prowler/providers/aws/services/iam/iam_no_root_access_key/iam_no_root_access_key.py | T7: =IF(OR(L7="critical",AND(L7="high",OR(K7="IAM",K7="network"))),"T3",IF(OR(L7="high",L7="medium"),"T2","T1")) -> T3
A8: P-007 | B8: 2.5 | C8: Ensure MFA is enabled for the 'root' user account | D8: 2 Identity and Access Management | E8: Level 1 | F8: Automated | G8: iam_root_mfa_enabled | H8: Root account has MFA enabled | I8: iam | J8: AwsIamUser | K8: IAM | L8: critical | M8: Without MFA, compromise of the root password or access keys can lead to full account takeover. An attacker with root can disable protections, steal or delete data, change billing, and create persistent admins, undermining confidentiality, integrity, and availability. | N8: Root account has credentials without MFA | O8: Root account has credentials with MFA enabled. | R8: https://docs.aws.amazon.com/IAM/latest/UserGuide/id_root-user.html#id_root-user_manage_mfa | S8: https://github.com/prowler-cloud/prowler/blob/master/prowler/providers/aws/services/iam/iam_root_mfa_enabled/iam_root_mfa_enabled.py | T8: =IF(OR(L8="critical",AND(L8="high",OR(K8="IAM",K8="network"))),"T3",IF(OR(L8="high",L8="medium"),"T2","T1")) -> T3
A9: P-008 | B9: 2.6 | C9: Ensure hardware MFA is enabled for the 'root' user account | D9: 2 Identity and Access Management | E9: Level 2 | F9: Manual | G9: iam_root_hardware_mfa_enabled | H9: Root account has a hardware MFA device enabled | I9: iam | J9: AwsIamUser | K9: IAM | L9: critical | M9: Without hardware MFA on the root user: - No MFA: stolen password/keys enable full account takeover. - Virtual MFA: device compromise or backup restoration weakens second-factor assurance. An attacker could delete resources, change policies, and disable logging, harming confidentiality, integrity, and availability. | N9: Root account has credentials with virtual MFA | O9: Root account has credentials with hardware MFA enabled. | R9: https://docs.aws.amazon.com/IAM/latest/UserGuide/id_root-user.html#id_root-user_manage_mfa | S9: https://github.com/prowler-cloud/prowler/blob/master/prowler/providers/aws/services/iam/iam_root_hardware_mfa_enabled/iam_root_hardware_mfa_enabled.py | T9: =IF(OR(L9="critical",AND(L9="high",OR(K9="IAM",K9="network"))),"T3",IF(OR(L9="high",L9="medium"),"T2","T1")) -> T3
A10: P-009 | B10: 2.7 | C10: Eliminate use of the 'root' user for administrative and daily tasks | D10: 2 Identity and Access Management | E10: Level 1 | F10: Manual | G10: iam_avoid_root_usage | H10: AWS account root user has not been used in the last day | I10: iam | J10: AwsIamUser | K10: IAM | L10: high | M10: Recent root usage expands blast radius: - Data exfiltration (confidentiality) - Policy/key tampering (integrity) - Resource deletion and billing changes (availability) Routine use reduces anomaly visibility and eases account takeover impact. | N10: Root user in the account was last accessed {days_since_accessed} days ago. | O10: Root user in the account wasn't accessed in the last {maximum_access_days} days. | R10: https://docs.aws.amazon.com/IAM/latest/UserGuide/root-user-best-practices.html | S10: https://github.com/prowler-cloud/prowler/blob/master/prowler/providers/aws/services/iam/iam_avoid_root_usage/iam_avoid_root_usage.py | T10: =IF(OR(L10="critical",AND(L10="high",OR(K10="IAM",K10="network"))),"T3",IF(OR(L10="high",L10="medium"),"T2","T1")) -> T3
A11: P-010 | B11: 2.8 | C11: Ensure IAM password policy requires minimum length of 14 or greater | D11: 2 Identity and Access Management | E11: Level 1 | F11: Automated | G11: iam_password_policy_minimum_length_14 | H11: IAM password policy requires passwords to be at least 14 characters long | I11: iam | J11: AwsIamPolicy | K11: IAM | L11: medium | M11: Low minimum length reduces entropy, easing brute force and credential stuffing. Compromised IAM users enable console access, unauthorized changes, and lateral movement, leading to data exposure (confidentiality) and tampering (integrity). | N11: IAM password policy does not require minimum length of 14 characters. | O11: IAM password policy requires minimum length of 14 characters. | P11: resource "aws_iam_account_password_policy" "<example_resource_name>" { minimum_password_length = 14 # Critical: enforces minimum password length >=14 } | Q11: aws iam update-account-password-policy --minimum-password-length 14 | R11: https://docs.aws.amazon.com/config/latest/developerguide/iam-password-policy.html https://docs.aws.amazon.com/IAM/latest/UserGuide/id_credentials_passwords_account-policy.html https://docs.aws.amazon.com/sdk-for-ruby/v3/api/Aws/IAM/Resource.html | S11: https://github.com/prowler-cloud/prowler/blob/master/prowler/providers/aws/services/iam/iam_password_policy_minimum_length_14/iam_password_policy_minimum_length_14.py | T11: =IF(OR(L11="critical",AND(L11="high",OR(K11="IAM",K11="network"))),"T3",IF(OR(L11="high",L11="medium"),"T2","T1")) -> T2
A12: P-011 | B12: 2.9 | C12: Ensure IAM password policy prevents password reuse | D12: 2 Identity and Access Management | E12: Level 1 | F12: Automated | G12: iam_password_policy_reuse_24 | H12: IAM password policy prevents reuse of the last 24 passwords | I12: iam | J12: AwsIamPolicy | K12: IAM | L12: medium | M12: If fewer than 24 passwords are remembered, users can cycle back to recent secrets, undermining rotation. Attackers with previously exposed passwords can regain console access after a change, reducing confidentiality and integrity and increasing success of credential-stuffing with known credentials. | N12: IAM password policy reuse prevention is less than 24 or not set. | O12: IAM password policy reuse prevention is equal to 24. | P12: resource "aws_iam_account_password_policy" "<example_resource_name>" { password_reuse_prevention = 24 # Critical: require last 24 passwords cannot be reused } | Q12: aws iam update-account-password-policy --password-reuse-prevention 24 | R12: https://docs.aws.amazon.com/IAM/latest/UserGuide/id_credentials_passwords_account-policy.html | S12: https://github.com/prowler-cloud/prowler/blob/master/prowler/providers/aws/services/iam/iam_password_policy_reuse_24/iam_password_policy_reuse_24.py | T12: =IF(OR(L12="critical",AND(L12="high",OR(K12="IAM",K12="network"))),"T3",IF(OR(L12="high",L12="medium"),"T2","T1")) -> T2
A13: P-012 | B13: 2.10 | C13: Ensure multi-factor authentication (MFA) is enabled for all IAM users that have a console password | D13: 2 Identity and Access Management | E13: Level 1 | F13: Automated | G13: iam_user_mfa_enabled_console_access | H13: IAM user has MFA enabled for console access or no console password is set | I13: iam | J13: AwsIamUser | K13: IAM | L13: high | M13: Without MFA, a stolen or brute-forced password grants full interactive access. Attackers can: - Change policies or keys - Exfiltrate data - Create backdoor users - Disable logging. This enables account takeover, threatens confidentiality and integrity, and can disrupt availability. | N13: User {user['user']} has Console Password enabled but MFA disabled. | O13: User {user['user']} has Console Password enabled and MFA enabled. | P13: # IAM user without console password resource "aws_iam_user" "user" { name = "<example_resource_name>" # Critical: Do NOT create an aws_iam_user_login_profile resource. # Without a login profile, no console password is set, so the check passes. } | Q13: aws iam delete-login-profile --user-name <IAM_USER_NAME> | R13: https://docs.aws.amazon.com/IAM/latest/UserGuide/id_credentials_mfa_enable_virtual.html | S13: https://github.com/prowler-cloud/prowler/blob/master/prowler/providers/aws/services/iam/iam_user_mfa_enabled_console_access/iam_user_mfa_enabled_console_access.py | T13: =IF(OR(L13="critical",AND(L13="high",OR(K13="IAM",K13="network"))),"T3",IF(OR(L13="high",L13="medium"),"T2","T1")) -> T3
A14: P-013 | B14: 2.11 | C14: Ensure credentials unused for 45 days or more are disabled | D14: 2 Identity and Access Management | E14: Level 1 | F14: Automated | G14: iam_user_accesskey_unused | H14: IAM user does not have unused access keys older than 45 days | I14: iam | J14: AwsIamUser | K14: IAM | L14: medium | M14: Active yet unused keys expand the attack surface. If leaked, adversaries gain API access for data exfiltration, unauthorized changes, and resource abuse, harming confidentiality, integrity, and availability. Stale credentials also enable persistence and unexpected cost spikes. | N14: User {user['user']} has not used access key 1 in the last {maximum_expiration_days} days ({access_key_1_last_used_date.days} days). | O14: User {user['user']} does not have access keys. | Q14: aws iam update-access-key --user-name <USER_NAME> --access-key-id <ACCESS_KEY_ID> --status Inactive | R14: https://docs.aws.amazon.com/IAM/latest/UserGuide/id_credentials_finding-unused.html https://docs.aws.amazon.com/securityhub/latest/userguide/iam-controls.html | S14: https://github.com/prowler-cloud/prowler/blob/master/prowler/providers/aws/services/iam/iam_user_accesskey_unused/iam_user_accesskey_unused.py | T14: =IF(OR(L14="critical",AND(L14="high",OR(K14="IAM",K14="network"))),"T3",IF(OR(L14="high",L14="medium"),"T2","T1")) -> T2
A15: P-014 | B15: 2.11 | C15: Ensure credentials unused for 45 days or more are disabled | D15: 2 Identity and Access Management | E15: Level 1 | F15: Automated | G15: iam_user_console_access_unused | H15: IAM user console access is disabled, used within the configured inactivity period, or never used | I15: iam | J15: AwsIamUser | K15: IAM | L15: medium | M15: Dormant console credentials stay valid and invite password spraying, credential stuffing, and breach reuse. Compromise yields interactive access for data discovery/exfiltration and unauthorized IAM or resource changes, degrading confidentiality and integrity, and risking availability. | N15: User {user.name} has not logged in to the console in the past {maximum_expiration_days} days ({time_since_insertion.days} days). | O15: User {user.name} has logged in to the console in the past {maximum_expiration_days} days ({time_since_insertion.days} days). | P15: # IAM user with console access disabled by not creating a login profile resource "aws_iam_user" "<example_resource_name>" { name = "<example_resource_name>" # Critical: Do not define aws_iam_user_login_profile for this user -> no console access } | Q15: aws iam delete-login-profile --user-name <USER_NAME> | R15: https://docs.aws.amazon.com/IAM/latest/UserGuide/id_credentials_finding-unused.html https://docs.aws.amazon.com/securityhub/latest/userguide/iam-controls.html | S15: https://github.com/prowler-cloud/prowler/blob/master/prowler/providers/aws/services/iam/iam_user_console_access_unused/iam_user_console_access_unused.py | T15: =IF(OR(L15="critical",AND(L15="high",OR(K15="IAM",K15="network"))),"T3",IF(OR(L15="high",L15="medium"),"T2","T1")) -> T2
A16: P-015 | B16: 2.12 | C16: Ensure access keys are rotated every 90 days or less | D16: 2 Identity and Access Management | E16: Level 1 | F16: Automated | G16: iam_rotate_access_key_90_days | H16: IAM user does not have active access keys older than 90 days | I16: iam | J16: AwsIamUser | K16: IAM | L16: medium | M16: Long-lived access keys widen the attack window. If a key is leaked in code, logs, or tooling, lack of rotation keeps it valid for abuse, enabling unauthorized API calls, data exfiltration, and tampering. This degrades confidentiality and integrity and can impact availability and cost through destructive or excessive operations. | N16: User {user['user']} has not rotated access key 1 in over 90 days ({access_key_1_last_rotated.days} days). | O16: User {user['user']} does not have access keys. | P16: resource "aws_iam_access_key" "<example_resource_name>" { user = "<example_resource_name>" status = "Inactive" # Critical: disables the access key to ensure no active key is older than 90 days } | Q16: aws iam update-access-key --user-name <USER_NAME> --access-key-id <ACCESS_KEY_ID> --status Inactive | R16: https://docs.aws.amazon.com/IAM/latest/UserGuide/id_credentials_getting-report.html | S16: https://github.com/prowler-cloud/prowler/blob/master/prowler/providers/aws/services/iam/iam_rotate_access_key_90_days/iam_rotate_access_key_90_days.py | T16: =IF(OR(L16="critical",AND(L16="high",OR(K16="IAM",K16="network"))),"T3",IF(OR(L16="high",L16="medium"),"T2","T1")) -> T2
A17: P-016 | B17: 2.13 | C17: Ensure IAM users receive permissions only through groups | D17: 2 Identity and Access Management | E17: Level 1 | F17: Automated | G17: iam_policy_attached_only_to_group_or_roles | H17: IAM user has no inline or attached policies | I17: iam | J17: AwsIamUser | K17: IAM | L17: low | M17: Directly attached user policies hinder centralized control and cause privilege creep. If a user is compromised, excessive rights enable data exposure, resource tampering, and lateral movement, harming confidentiality and integrity. Revocation is error-prone, weakening separation of duties and auditability. | N17: User {user.name} has the policy {policy['PolicyName']} attached. | O17: User {user.name} has no inline or attached policies. | R17: https://docs.aws.amazon.com/securityhub/latest/userguide/iam-controls.html https://docs.aws.amazon.com/IAM/latest/UserGuide/best-practices.html | S17: https://github.com/prowler-cloud/prowler/blob/master/prowler/providers/aws/services/iam/iam_policy_attached_only_to_group_or_roles/iam_policy_attached_only_to_group_or_roles.py | T17: =IF(OR(L17="critical",AND(L17="high",OR(K17="IAM",K17="network"))),"T3",IF(OR(L17="high",L17="medium"),"T2","T1")) -> T1
A18: P-017 | B18: 2.14 | C18: Ensure IAM policies that allow full "*:*" administrative privileges are not attached | D18: 2 Identity and Access Management | E18: Level 1 | F18: Automated | G18: iam_aws_attached_policy_no_administrative_privileges | H18: Attached AWS-managed IAM policy does not allow ':' administrative privileges | I18: iam | J18: AwsIamPolicy | K18: IAM | L18: critical | M18: Unrestricted : access enables any action on any resource, risking: - Data exfiltration (confidentiality) - Unauthorized changes and policy tampering (integrity) - Service deletion or shutdown (availability) Attackers can disable logging, create backdoor principals, and expand lateral movement. | N18: {policy.type} policy {policy.name} is attached and allows '*:*' administrative privileges. | O18: {policy.type} policy {policy.name} is attached but does not allow '*:*' administrative privileges. | P18: # Replace full admin attachment with a non-admin policy (ensure AdministratorAccess is not attached) resource "aws_iam_role_policy_attachment" "<example_resource_name>" { role = "<example_resource_name>" policy_arn = "arn:aws:iam::aws:policy/ReadOnlyAccess" # FIX: avoids ':' admin privileges; replace AdministratorAccess } | R18: https://docs.aws.amazon.com/aws-managed-policy/latest/reference/AdministratorAccess.html http://docs.aws.amazon.com/IAM/latest/UserGuide/best-practices.html | S18: https://github.com/prowler-cloud/prowler/blob/master/prowler/providers/aws/services/iam/iam_aws_attached_policy_no_administrative_privileges/iam_aws_attached_policy_no_administrative_privileges.py | T18: =IF(OR(L18="critical",AND(L18="high",OR(K18="IAM",K18="network"))),"T3",IF(OR(L18="high",L18="medium"),"T2","T1")) -> T3
A19: P-018 | B19: 2.14 | C19: Ensure IAM policies that allow full "*:*" administrative privileges are not attached | D19: 2 Identity and Access Management | E19: Level 1 | F19: Automated | G19: iam_customer_attached_policy_no_administrative_privileges | H19: Attached IAM customer-managed policy does not allow ':' administrative privileges | I19: iam | J19: AwsIamPolicy | K19: IAM | L19: high | M19: Unrestricted admin access lets any attached principal perform any action on any resource, enabling data exfiltration, policy tampering, credential creation, logging disablement, and destructive deletions-compromising confidentiality, integrity, and availability across the account. | N19: {policy.type} policy {policy.name} is attached and allows '*:*' administrative privileges. | O19: {policy.type} policy {policy.name} is attached but does not allow '*:*' administrative privileges. | P19: # Terraform: Managed policy without ':' admin privileges resource "aws_iam_policy" "<example_resource_name>" { name = "<example_resource_name>" policy = jsonencode({ Version = "2012-10-17" Statement = [{ Effect = "Allow" Action = "iam:GetUser" # CRITICAL: not "" or ":"; removes admin privileges Resource = "" # CRITICAL: paired with specific action to avoid full admin }] }) } | Q19: aws iam create-policy-version --policy-arn <EXAMPLE_POLICY_ARN> --policy-document '{"Version":"2012-10-17","Statement":[{"Effect":"Allow","Action":"iam:GetUser","Resource":""}]}' --set-as-default | R19: http://docs.aws.amazon.com/IAM/latest/UserGuide/best-practices.html | S19: https://github.com/prowler-cloud/prowler/blob/master/prowler/providers/aws/services/iam/iam_customer_attached_policy_no_administrative_privileges/iam_customer_attached_policy_no_administrative_privileges.py | T19: =IF(OR(L19="critical",AND(L19="high",OR(K19="IAM",K19="network"))),"T3",IF(OR(L19="high",L19="medium"),"T2","T1")) -> T3
A20: P-019 | B20: 2.15 | C20: Ensure a support role has been created to manage incidents with AWS Support | D20: 2 Identity and Access Management | E20: Level 1 | F20: Automated | G20: iam_support_role_created | H20: At least one IAM role has the AWSSupportAccess managed policy attached | I20: iam | J20: AwsIamRole | K20: IAM | L20: low | M20: Without a dedicated support role: - Case creation and escalation can be delayed, prolonging outages (availability) - Teams may use admin/root, increasing blast radius (confidentiality/integrity) - Audit trails of support actions are weaker, hindering investigations | N20: AWS Support Access policy is not attached to any role. | O20: AWS Support Access policy attached to role {iam_client.entities_role_attached_to_support_policy[0]['RoleName']}. | P20: # IAM role with AWS Support access resource "aws_iam_role" "example_resource_name" { name = "example_resource_name" assume_role_policy = jsonencode({ Version = "2012-10-17", Statement = [{ Effect = "Allow", Principal = { AWS = "arn:aws:iam::<example_account_id>:user/<example_resource_name>" }, Action = "sts:AssumeRole" }] }) managed_policy_arns = [ "arn:aws:iam::aws:policy/AWSSupportAccess" # Critical: ensures this role has AWSSupportAccess (PASS) ] } | Q20: aws iam attach-role-policy --role-name <example_resource_name> --policy-arn arn:aws:iam::aws:policy/AWSSupportAccess | R20: https://docs.aws.amazon.com/awssupport/latest/user/using-service-linked-roles-sup.html https://docs.aws.amazon.com/aws-managed-policy/latest/reference/AWSSupportAccess.html | S20: https://github.com/prowler-cloud/prowler/blob/master/prowler/providers/aws/services/iam/iam_support_role_created/iam_support_role_created.py | T20: =IF(OR(L20="critical",AND(L20="high",OR(K20="IAM",K20="network"))),"T3",IF(OR(L20="high",L20="medium"),"T2","T1")) -> T1
A21: P-020 | B21: 2.16 | C21: Ensure IAM instance roles are used for AWS resource access from instances | D21: 2 Identity and Access Management | E21: Level 2 | F21: Automated | G21: ec2_instance_profile_attached | H21: EC2 instance is associated with an IAM instance profile role | I21: ec2 | J21: AwsEc2Instance | K21: compute | L21: medium | M21: Without an instance profile, apps often rely on long-term access keys on the host. Exposed keys can be used from anywhere to read data, alter resources, or disrupt services, impacting confidentiality, integrity, and availability. Keys may persist in AMIs, images, or logs, hindering rotation and amplifying blast radius. | N21: EC2 Instance {instance.id} not associated with an Instance Profile Role. | O21: EC2 Instance {instance.id} associated with Instance Profile Role {instance.instance_profile['Arn']}. | P21: # Attach an IAM instance profile to the EC2 instance resource "aws_instance" "example" { ami = "<AMI_ID>" instance_type = "<INSTANCE_TYPE>" iam_instance_profile = "<INSTANCE_PROFILE_NAME>" # Critical: associates an instance profile so the check passes } | Q21: aws ec2 associate-iam-instance-profile --instance-id <INSTANCE_ID> --iam-instance-profile Name=<INSTANCE_PROFILE_NAME> | R21: http://docs.aws.amazon.com/IAM/latest/UserGuide/id_roles_use_switch-role-ec2.html | S21: https://github.com/prowler-cloud/prowler/blob/master/prowler/providers/aws/services/ec2/ec2_instance_profile_attached/ec2_instance_profile_attached.py | T21: =IF(OR(L21="critical",AND(L21="high",OR(K21="IAM",K21="network"))),"T3",IF(OR(L21="high",L21="medium"),"T2","T1")) -> T2
A22: P-021 | B22: 2.17 | C22: Ensure that all expired SSL/TLS certificates stored in AWS IAM are removed | D22: 2 Identity and Access Management | E22: Level 1 | F22: Automated | G22: iam_no_expired_server_certificates_stored | H22: IAM server certificate is not expired | I22: iam | J22: AwsCertificateManagerCertificate | K22: IAM | L22: high | M22: Retaining expired TLS certificates risks availability loss from failed handshakes and browser warnings, eroding trust. If attached to endpoints, users may bypass warnings, weakening confidentiality and integrity. Stale certs also hinder secure rotation and may be picked by automation, causing outages. | N22: IAM Certificate {certificate.name} has expired {expiration_days} days ago. | O22: IAM Certificate {certificate.name} is not expired. | Q22: aws iam delete-server-certificate --server-certificate-name <CERTIFICATE_NAME> | R22: https://docs.aws.amazon.com/IAM/latest/UserGuide/id_credentials_server-certs.html | S22: https://github.com/prowler-cloud/prowler/blob/master/prowler/providers/aws/services/iam/iam_no_expired_server_certificates_stored/iam_no_expired_server_certificates_stored.py | T22: =IF(OR(L22="critical",AND(L22="high",OR(K22="IAM",K22="network"))),"T3",IF(OR(L22="high",L22="medium"),"T2","T1")) -> T3
A23: P-022 | B23: 2.18 | C23: Ensure that IAM External Access Analyzer is enabled for all regions | D23: 2 Identity and Access Management | E23: Level 1 | F23: Automated | G23: accessanalyzer_enabled | H23: IAM Access Analyzer is enabled | I23: accessanalyzer | J23: Other | K23: security | L23: low | M23: Without an active analyzer, visibility into unintended public, cross-account, or risky internal access is lost. Adversaries can exploit exposed S3, snapshots, KMS keys, or permissive role trusts for data exfiltration and escalation. Unused permissions persist, enlarging the attack surface. This degrades confidentiality and integrity. | N23: IAM Access Analyzer in account {accessanalyzer_client.audited_account} is not enabled. | O23: IAM Access Analyzer {analyzer.name} is enabled. | P23: resource "aws_accessanalyzer_analyzer" "example_resource" { analyzer_name = "example_resource" type = "ACCOUNT" # This line fixes the security issue } | Q23: aws accessanalyzer create-analyzer --analyzer-name example_resource --type ACCOUNT | R23: https://docs.aws.amazon.com/IAM/latest/UserGuide/access-analyzer-manage-external.html https://aws.amazon.com/iam/access-analyzer/ https://docs.aws.amazon.com/IAM/latest/UserGuide/access-analyzer-getting-started.html https://docs.aws.amazon.com/access-analyzer/latest/APIReference/API_CreateAnalyzer.html https://docs.aws.amazon.com/IAM/latest/UserGuide/what-is-access-analyzer.html https://docs.aws.amazon.com/IAM/latest/UserGuide/access-analyzer-create-external.html https://docs.aws.amazon.com/access-analyzer/latest/APIReference/Welcome.html https://docs.aws.amazon.com/IAM/latest/UserGuide/access-analyzer-create-internal.html | S23: https://github.com/prowler-cloud/prowler/blob/master/prowler/providers/aws/services/accessanalyzer/accessanalyzer_enabled/accessanalyzer_enabled.py | T23: =IF(OR(L23="critical",AND(L23="high",OR(K23="IAM",K23="network"))),"T3",IF(OR(L23="high",L23="medium"),"T2","T1")) -> T1
A24: P-023 | B24: 2.19 | C24: Ensure IAM users are managed centrally via identity federation or AWS Organizations for multi-account environments | D24: 2 Identity and Access Management | E24: Level 2 | F24: Manual | G24: iam_check_saml_providers_sts | H24: IAM SAML provider exists in the account | I24: iam | J24: Other | K24: IAM | L24: low | M24: Without SAML federation, users rely on long-lived IAM keys. Compromised keys enable persistent API access, causing data exfiltration (C), unauthorized resource or policy changes (I), and difficult revocation. Lack of IdP controls (e.g., MFA, session limits) weakens accountability and access governance. | N24: No SAML Providers found. | O24: SAML Provider {provider.name} has been found. | P24: # Create an IAM SAML provider to satisfy the check resource "aws_iam_saml_provider" "<example_resource_name>" { name = "<example_resource_name>" saml_metadata_document = file("<SAML_METADATA_XML_FILE>") # Critical: creates the SAML provider so the check passes } | Q24: aws iam create-saml-provider --name <SAML_PROVIDER_NAME> --saml-metadata-document file://<SAML_METADATA_XML_FILE> | R24: https://docs.aws.amazon.com/STS/latest/APIReference/API_AssumeRoleWithSAML.html | S24: https://github.com/prowler-cloud/prowler/blob/master/prowler/providers/aws/services/iam/iam_check_saml_providers_sts/iam_check_saml_providers_sts.py | T24: =IF(OR(L24="critical",AND(L24="high",OR(K24="IAM",K24="network"))),"T3",IF(OR(L24="high",L24="medium"),"T2","T1")) -> T1
A25: P-024 | B25: 2.20 | C25: Ensure access to AWSCloudShellFullAccess is restricted | D25: 2 Identity and Access Management | E25: Level 1 | F25: Manual | G25: iam_policy_cloudshell_admin_not_attached | H25: No IAM users, groups, or roles have the AWSCloudShellFullAccess policy attached | I25: iam | J25: AwsIamPolicy | K25: IAM | L25: medium | M25: Granting cloudshell: enables an interactive shell with Internet egress and file upload/download, degrading confidentiality and integrity. Compromised principals can exfiltrate data, stage tooling with sudo, persist artifacts in CloudShell, and operate from AWS IP space to bypass endpoint controls. | N25: AWS CloudShellFullAccess policy attached to IAM {', '.join(entity_strings)}. | O25: AWS CloudShellFullAccess policy is not attached to any IAM entity. | P25: # Terraform: ensure AWSCloudShellFullAccess is NOT attached resource "aws_iam_user_policy_attachment" "<example_resource_name>" { count = 0 # Critical: prevents creation, ensuring the policy is detached/not attached user = "<example_resource_name>" policy_arn = "arn:aws:iam::aws:policy/AWSCloudShellFullAccess" # Denied policy } | R25: https://docs.aws.amazon.com/securityhub/latest/userguide/iam-controls.html#iam-27 https://docs.aws.amazon.com/config/latest/developerguide/iam-policy-blacklisted-check.html https://docs.aws.amazon.com/IAM/latest/UserGuide/access_policies_manage-attach-detach.html | S25: https://github.com/prowler-cloud/prowler/blob/master/prowler/providers/aws/services/iam/iam_policy_cloudshell_admin_not_attached/iam_policy_cloudshell_admin_not_attached.py | T25: =IF(OR(L25="critical",AND(L25="high",OR(K25="IAM",K25="network"))),"T3",IF(OR(L25="high",L25="medium"),"T2","T1")) -> T2
A26: P-025 | B26: 2.21 | C26: Ensure AWS resource policies do not allow unrestricted access using 'Principal': '*' | D26: 2 Identity and Access Management | E26: Level 1 | F26: Manual | G26: s3_bucket_policy_public_write_access | H26: S3 bucket policy does not allow public write access | I26: s3 | J26: AwsS3Bucket | K26: storage | L26: critical | M26: Public write access lets anyone upload, overwrite, or delete objects, undermining integrity and availability. Attackers can plant malware, stage phishing content, poison data, or wipe buckets, causing outages and potential legal and cost impacts from storage abuse and content hosting. | N26: S3 Bucket {bucket.name} allows public write access in the bucket policy. | O26: S3 Bucket {bucket.name} does not have a bucket policy. | P26: # Enable bucket-level Public Access Block so public bucket policies (including write) are blocked resource "aws_s3_bucket_public_access_block" "<example_resource_name>" { bucket = "<example_resource_id>" restrict_public_buckets = true # Critical: prevents public access granted via bucket policies } | Q26: aws s3api put-public-access-block --bucket <BUCKET_NAME> --public-access-block-configuration RestrictPublicBuckets=true | R26: https://docs.aws.amazon.com/IAM/latest/UserGuide/reference_policies_examples_s3_rw-bucket.html | S26: https://github.com/prowler-cloud/prowler/blob/master/prowler/providers/aws/services/s3/s3_bucket_policy_public_write_access/s3_bucket_policy_public_write_access.py | T26: =IF(OR(L26="critical",AND(L26="high",OR(K26="IAM",K26="network"))),"T3",IF(OR(L26="high",L26="medium"),"T2","T1")) -> T3
A27: P-026 | B27: 2.21 | C27: Ensure AWS resource policies do not allow unrestricted access using 'Principal': '*' | D27: 2 Identity and Access Management | E27: Level 1 | F27: Manual | G27: sqs_queues_not_publicly_accessible | H27: SQS queue policy does not allow public access | I27: sqs | J27: AwsSqsQueue | K27: messaging | L27: critical | M27: Public SQS access can expose message data (confidentiality), enable unauthorized send/receive or tampering (integrity), and allow purge/delete operations that disrupt processing (availability). It may also trigger unbounded message ingestion, causing cost spikes and consumer overload. | N27: SQS queue {queue.id} is public because its policy allows public access, and the condition does not limit access to resources within the same account. | O27: SQS queue {queue.id} is not public. | P27: # Restrict SQS policy to a specific principal (not public) resource "aws_sqs_queue_policy" "<example_resource_name>" { queue_url = "<example_queue_url>" policy = jsonencode({ Version = "2012-10-17" Statement = [{ Effect = "Allow" Principal = { AWS = "<example_account_id>" } # CRITICAL: restrict to a specific principal (removes public "") Action = "sqs:" Resource = "<example_queue_arn>" }] }) } | Q27: aws sqs set-queue-attributes --queue-url <example_queue_url> --attributes Policy='{"Version":"2012-10-17","Statement":[{"Effect":"Allow","Principal":{"AWS":"<example_account_id>"},"Action":"sqs:","Resource":"<example_queue_arn>"}]}' | R27: https://docs.aws.amazon.com/AWSSimpleQueueService/latest/SQSDeveloperGuide/sqs-basic-examples-of-sqs-policies.html | S27: https://github.com/prowler-cloud/prowler/blob/master/prowler/providers/aws/services/sqs/sqs_queues_not_publicly_accessible/sqs_queues_not_publicly_accessible.py | T27: =IF(OR(L27="critical",AND(L27="high",OR(K27="IAM",K27="network"))),"T3",IF(OR(L27="high",L27="medium"),"T2","T1")) -> T3
A28: P-027 | B28: 2.21 | C28: Ensure AWS resource policies do not allow unrestricted access using 'Principal': '*' | D28: 2 Identity and Access Management | E28: Level 1 | F28: Manual | G28: sns_topics_not_publicly_accessible | H28: SNS topic is not publicly accessible | I28: sns | J28: AwsSnsTopic | K28: messaging | L28: high | M28: Public SNS topics allow anyone or unknown accounts to: - Subscribe and siphon messages (confidentiality) - Publish spoofed payloads that alter workflows (integrity) - Flood messages causing outages and costs (availability) They also enable cross-account abuse and bypass expected trust boundaries. | N28: SNS topic {topic.name} is public because its policy allows public access. | O28: SNS topic {topic.name} is not publicly accessible. | P28: # Restrict SNS topic policy to the account (not public) resource "aws_sns_topic_policy" "<example_resource_name>" { arn = "<TOPIC_ARN>" policy = jsonencode({ Version = "2012-10-17" Statement = [{ Effect = "Allow" Action = "sns:Publish" Resource = "<TOPIC_ARN>" Principal = { AWS = "arn:aws:iam::<ACCOUNT_ID>:root" } # Critical: restrict principal to the account to remove public access }] }) } | Q28: aws sns set-topic-attributes --topic-arn <TOPIC_ARN> --attribute-name Policy --attribute-value '{"Version":"2012-10-17","Statement":[{"Effect":"Allow","Principal":{"AWS":"arn:aws:iam::<ACCOUNT_ID>:root"},"Action":"sns:Publish","Resource":"<TOPIC_ARN>"}]}' | R28: https://docs.aws.amazon.com/config/latest/developerguide/sns-topic-policy.html | S28: https://github.com/prowler-cloud/prowler/blob/master/prowler/providers/aws/services/sns/sns_topics_not_publicly_accessible/sns_topics_not_publicly_accessible.py | T28: =IF(OR(L28="critical",AND(L28="high",OR(K28="IAM",K28="network"))),"T3",IF(OR(L28="high",L28="medium"),"T2","T1")) -> T2
A29: P-028 | B29: 2.21 | C29: Ensure AWS resource policies do not allow unrestricted access using 'Principal': '*' | D29: 2 Identity and Access Management | E29: Level 1 | F29: Manual | G29: awslambda_function_not_publicly_accessible | H29: Lambda function resource-based policy does not allow public access | I29: awslambda | J29: AwsLambdaFunction | K29: serverless | L29: critical | M29: Public invocation lets outsiders run code under the function's IAM role. Impacts: - Confidentiality: data exfiltration via backend access - Integrity: unauthorized state changes from side effects - Availability/cost: invocation floods causing throttling and spend spikes | N29: Lambda function {function.name} has a resource-based policy with public access. | O29: Lambda function {function.name} has a resource-based policy without public access. | P29: # Restrict Lambda permission to a non-public principal resource "aws_lambda_permission" "<example_resource_name>" { statement_id = "AllowSpecificPrincipal" action = "lambda:InvokeFunction" function_name = "<example_resource_name>" principal = "123456789012" # Critical: not ""; prevents public access } | Q29: aws lambda remove-permission --function-name <example_function_name> --statement-id <example_statement_id> | R29: https://docs.aws.amazon.com/config/latest/developerguide/lambda-function-public-access-prohibited.html https://docs.aws.amazon.com/lambda/latest/dg/access-control-resource-based.html https://docs.aws.amazon.com/securityhub/latest/userguide/lambda-controls.html | S29: https://github.com/prowler-cloud/prowler/blob/master/prowler/providers/aws/services/awslambda/awslambda_function_not_publicly_accessible/awslambda_function_not_publicly_accessible.py | T29: =IF(OR(L29="critical",AND(L29="high",OR(K29="IAM",K29="network"))),"T3",IF(OR(L29="high",L29="medium"),"T2","T1")) -> T3
A30: P-029 | B30: 2.21 | C30: Ensure AWS resource policies do not allow unrestricted access using 'Principal': '*' | D30: 2 Identity and Access Management | E30: Level 1 | F30: Manual | G30: kms_key_not_publicly_accessible | H30: Cloud KMS key does not grant access to allUsers or allAuthenticatedUsers | I30: kms | J30: AwsKmsKey | K30: security | L30: critical | M30: Broad access to a KMS key enables unauthorized kms:Decrypt and data-key generation, breaking confidentiality. With admin rights, attackers can change policies or schedule deletion, undermining control integrity and threatening availability of data dependent on the key. | N30: KMS key {key.id} may be publicly accessible. | O30: KMS key {key.id} is not exposed to Public. | P30: # Restrict KMS key policy to the account root to avoid any public ("") principals data "aws_caller_identity" "current" {} resource "aws_kms_key" "<example_resource_name>" { policy = jsonencode({ Version = "2012-10-17" Statement = [ { Effect = "Allow" Principal = { AWS = "arn:aws:iam::${data.aws_caller_identity.current.account_id}:root" } # Critical: limit to account root to remove public access Action = "kms:" Resource = "" } ] }) } | Q30: aws kms put-key-policy --key-id <example_resource_id> --policy-name default --policy '{"Version":"2012-10-17","Statement":[{"Effect":"Allow","Principal":{"AWS":"arn:aws:iam::<account_id>:root"},"Action":"kms:\","Resource":"\"}]}' | R30: https://docs.aws.amazon.com/kms/latest/developerguide/determining-access.html | S30: https://github.com/prowler-cloud/prowler/blob/master/prowler/providers/aws/services/kms/kms_key_not_publicly_accessible/kms_key_not_publicly_accessible.py | T30: =IF(OR(L30="critical",AND(L30="high",OR(K30="IAM",K30="network"))),"T3",IF(OR(L30="high",L30="medium"),"T2","T1")) -> T3
A31: P-030 | B31: 2.21 | C31: Ensure AWS resource policies do not allow unrestricted access using 'Principal': '*' | D31: 2 Identity and Access Management | E31: Level 1 | F31: Manual | G31: glacier_vaults_policy_public_access | H31: S3 Glacier vault has no policy or its policy does not allow access to everyone | I31: glacier | J31: Other | K31: storage | L31: critical | M31: Publicly grantable vault access undermines confidentiality and integrity. Anyone could list, retrieve, or delete archives, leading to data exposure or loss. Attackers may also trigger large retrieval operations, degrading availability and driving unexpected costs. | N31: Vault {vault.name} has policy which allows access to everyone. | O31: Vault {vault.name} has policy which does not allow access to everyone. | P31: # Glacier vault with no access policy (not public) resource "aws_glacier_vault" "<example_resource_name>" { name = "<example_resource_name>" # access_policy omitted to remove any public access and pass the check } | Q31: aws glacier delete-vault-access-policy --account-id <ACCOUNT_ID> --vault-name <VAULT_NAME> | R31: https://docs.aws.amazon.com/amazonglacier/latest/dev/access-control-overview.html | S31: https://github.com/prowler-cloud/prowler/blob/master/prowler/providers/aws/services/glacier/glacier_vaults_policy_public_access/glacier_vaults_policy_public_access.py | T31: =IF(OR(L31="critical",AND(L31="high",OR(K31="IAM",K31="network"))),"T3",IF(OR(L31="high",L31="medium"),"T2","T1")) -> T3
A32: P-031 | B32: 2.21 | C32: Ensure AWS resource policies do not allow unrestricted access using 'Principal': '*' | D32: 2 Identity and Access Management | E32: Level 1 | F32: Manual | G32: secretsmanager_not_publicly_accessible | H32: Secrets Manager secret resource policy does not allow public access | I32: secretsmanager | J32: AwsSecretsManagerSecret | K32: security | L32: high | M32: Public access to a secret enables uncontrolled retrieval of secret values, compromising confidentiality. If broad actions are allowed, attackers can modify or delete the secret, impacting integrity and availability, and use exposed credentials for unauthorized data access and lateral movement. | N32: SecretsManager secret {secret.name} is publicly accessible due to its resource policy. | O32: SecretsManager secret {secret.name} is not publicly accessible. | P32: # Restrict secret policy and block public access resource "aws_secretsmanager_secret_policy" "<example_resource_name>" { secret_arn = "<example_resource_id>" block_public_policy = true # Critical: blocks public policies policy = jsonencode({ # Critical: principal is not "" Version = "2012-10-17" Statement = [{ Effect = "Allow" Principal = { AWS = "arn:aws:iam::<ACCOUNT_ID>:root" } Action = "secretsmanager:GetSecretValue" Resource = "" }] }) } | Q32: aws secretsmanager put-resource-policy --secret-id <secret-id> --resource-policy '{"Version":"2012-10-17","Statement":[{"Effect":"Allow","Principal":{"AWS":"arn:aws:iam::<ACCOUNT_ID>:root"},"Action":"secretsmanager:GetSecretValue","Resource":""}]}' --block-public-policy | R32: https://docs.aws.amazon.com/secretsmanager/latest/userguide/auth-and-access_resource-policies.html https://docs.aws.amazon.com/secretsmanager/latest/userguide/determine-acccess_examine-iam-policies.html | S32: https://github.com/prowler-cloud/prowler/blob/master/prowler/providers/aws/services/secretsmanager/secretsmanager_not_publicly_accessible/secretsmanager_not_publicly_accessible.py | T32: =IF(OR(L32="critical",AND(L32="high",OR(K32="IAM",K32="network"))),"T3",IF(OR(L32="high",L32="medium"),"T2","T1")) -> T2
A33: P-032 | B33: 2.21 | C33: Ensure AWS resource policies do not allow unrestricted access using 'Principal': '*' | D33: 2 Identity and Access Management | E33: Level 1 | F33: Manual | G33: eventbridge_bus_exposed | H33: AWS EventBridge event bus policy does not allow public access | I33: eventbridge | J33: AwsEventsEventbus | K33: messaging | L33: high | M33: Publicly accessible event buses enable event injection and unauthorized rule changes, undermining integrity and enabling lateral movement. Attackers can trigger downstream targets, causing data exposure, service disruption, and unexpected costs through high-volume events. | N33: EventBridge event bus {bus.name} is exposed to everyone. | O33: EventBridge event bus {bus.name} is not exposed to everyone. | P33: resource "aws_cloudwatch_event_bus_policy" "<example_resource_name>" { # CRITICAL: Principal is a specific AWS account, not "", preventing public access policy = <<POLICY { "Version": "2012-10-17", "Statement": [{ "Sid": "AllowSpecificAccount", "Effect": "Allow", "Principal": {"AWS": "arn:aws:iam::<example_account_id>:root"}, "Action": "events:PutEvents", "Resource": "arn:aws:events:<example_region>:<example_account_id>:event-bus/default" }] } POLICY } | Q33: aws events remove-permission --event-bus-name <event_bus_name> --statement-id <statement_id> | R33: https://docs.aws.amazon.com/AmazonCloudWatch/latest/events/CloudWatchEvents-CrossAccountEventDelivery.html https://docs.aws.amazon.com/AmazonCloudWatch/latest/events/CWE_GettingStarted.html https://aws.amazon.com/blogs/compute/simplifying-cross-account-access-with-amazon-eventbridge-resource-policies/ | S33: https://github.com/prowler-cloud/prowler/blob/master/prowler/providers/aws/services/eventbridge/eventbridge_bus_exposed/eventbridge_bus_exposed.py | T33: =IF(OR(L33="critical",AND(L33="high",OR(K33="IAM",K33="network"))),"T3",IF(OR(L33="high",L33="medium"),"T2","T1")) -> T2
A34: P-033 | B34: 3.1.1 | C34: Ensure S3 Bucket Policy is set to deny HTTP requests | D34: 3 Storage | E34: Level 2 | F34: Automated | G34: s3_bucket_secure_transport_policy | H34: S3 bucket policy denies requests over insecure transport | I34: s3 | J34: AwsS3Bucket | K34: storage | L34: medium | M34: HTTP access exposes object data and auth details to eavesdropping and man-in-the-middle attacks. Captured pre-signed URLs can be replayed to exfiltrate data. Traffic can be intercepted or altered, undermining confidentiality and integrity of S3 content. | N34: S3 Bucket {bucket.name} does not have a bucket policy, thus it allows HTTP requests. | O34: S3 Bucket {bucket.name} has a bucket policy to deny requests over insecure transport. | P34: # Deny non-SSL (HTTP) requests to the S3 bucket resource "aws_s3_bucket_policy" "policy" { bucket = "<example_resource_name>" policy = jsonencode({ Version = "2012-10-17" Statement = [{ Effect = "Deny" Principal = "" Action = "s3:" Resource = "arn:aws:s3:::<example_resource_name>/" Condition = { Bool = { "aws:SecureTransport" = "false" # Critical: deny requests not using SSL/TLS } } }] }) } | Q34: aws s3api put-bucket-policy --bucket <example_resource_name> --policy '{"Version":"2012-10-17","Statement":[{"Effect":"Deny","Principal":"","Action":"s3:","Resource":"arn:aws:s3:::<example_resource_name>/","Condition":{"Bool":{"aws:SecureTransport":"false"}}}]}' | R34: https://aws.amazon.com/premiumsupport/knowledge-center/s3-bucket-policy-for-config-rule/ | S34: https://github.com/prowler-cloud/prowler/blob/master/prowler/providers/aws/services/s3/s3_bucket_secure_transport_policy/s3_bucket_secure_transport_policy.py | T34: =IF(OR(L34="critical",AND(L34="high",OR(K34="IAM",K34="network"))),"T3",IF(OR(L34="high",L34="medium"),"T2","T1")) -> T2
A35: P-034 | B35: 3.1.2 | C35: Ensure MFA Delete is enabled on S3 buckets | D35: 3 Storage | E35: Level 2 | F35: Manual | G35: s3_bucket_no_mfa_delete | H35: S3 bucket has MFA Delete enabled | I35: s3 | J35: AwsS3Bucket | K35: storage | L35: medium | M35: Without MFA Delete, a compromised or over-privileged identity can irrevocably purge object history or change versioning. This erases recovery points, degrading data availability, weakening integrity, and increasing the blast radius of account compromise or ransomware. | N35: S3 Bucket {bucket.name} has MFA Delete disabled. | O35: S3 Bucket {bucket.name} has MFA Delete enabled. | Q35: aws s3api put-bucket-versioning --bucket <BUCKET_NAME> --versioning-configuration Status=Enabled,MFADelete=Enabled --mfa "<MFA_SERIAL_OR_ARN> <MFA_CODE>" | R35: https://docs.aws.amazon.com/AmazonS3/latest/userguide/MultiFactorAuthenticationDelete.html https://docs.aws.amazon.com/AmazonS3/latest/userguide/UsingMFADelete.html | S35: https://github.com/prowler-cloud/prowler/blob/master/prowler/providers/aws/services/s3/s3_bucket_no_mfa_delete/s3_bucket_no_mfa_delete.py | T35: =IF(OR(L35="critical",AND(L35="high",OR(K35="IAM",K35="network"))),"T3",IF(OR(L35="high",L35="medium"),"T2","T1")) -> T2
A36: P-035 | B36: 3.1.3 | C36: Ensure all data in Amazon S3 has been discovered, classified, and secured when necessary | D36: 3 Storage | E36: Level 2 | F36: Manual | G36: macie_is_enabled | H36: Amazon Macie is enabled | I36: macie | J36: Other | K36: security | L36: medium | M36: Without active Macie, sensitive data in S3 can remain unclassified and exposed. Misconfigured access and public buckets may go undetected, enabling data exfiltration and secret leakage. This degrades confidentiality and widens breach blast radius by reducing visibility into where sensitive data resides. | N36: Macie is currently in a SUSPENDED state. | O36: Macie is enabled. | P36: # Enables Amazon Macie in this region resource "aws_macie2_account" "main" { # Critical: Creating this resource enables Macie for the account in the region } | Q36: aws macie2 enable-macie --region <REGION> | R36: https://aws.amazon.com/macie/getting-started/ | S36: https://github.com/prowler-cloud/prowler/blob/master/prowler/providers/aws/services/macie/macie_is_enabled/macie_is_enabled.py | T36: =IF(OR(L36="critical",AND(L36="high",OR(K36="IAM",K36="network"))),"T3",IF(OR(L36="high",L36="medium"),"T2","T1")) -> T2
A37: P-036 | B37: 3.1.4 | C37: Ensure that S3 is configured with 'Block Public Access' enabled | D37: 3 Storage | E37: Level 1 | F37: Automated | G37: s3_bucket_level_public_access_block | H37: S3 bucket has Block Public Access with IgnorePublicAcls and RestrictPublicBuckets enabled at bucket or account level | I37: s3 | J37: AwsS3Bucket | K37: storage | L37: high | M37: Absent S3 Block Public Access, public ACLs or broad policies can grant Internet or cross-account access. - Data disclosure (confidentiality) - Object overwrite or uploads (integrity) - Deletion or outages from misuse (availability) | N37: Block Public Access is not configured for the S3 Bucket {bucket.name}. | O37: Block Public Access is configured for the S3 Bucket {bucket.name}. | P37: # Enable required S3 Block Public Access settings on a bucket resource "aws_s3_bucket_public_access_block" "<example_resource_name>" { bucket = "<example_resource_id>" ignore_public_acls = true # CRITICAL: Ignore public ACLs restrict_public_buckets = true # CRITICAL: Restrict public buckets } | Q37: aws s3api put-public-access-block --bucket <BUCKET_NAME> --public-access-block-configuration IgnorePublicAcls=true,RestrictPublicBuckets=true | R37: https://docs.aws.amazon.com/AmazonS3/latest/userguide/access-control-block-public-access.html | S37: https://github.com/prowler-cloud/prowler/blob/master/prowler/providers/aws/services/s3/s3_bucket_level_public_access_block/s3_bucket_level_public_access_block.py | T37: =IF(OR(L37="critical",AND(L37="high",OR(K37="IAM",K37="network"))),"T3",IF(OR(L37="high",L37="medium"),"T2","T1")) -> T2
A38: P-037 | B38: 3.1.4 | C38: Ensure that S3 is configured with 'Block Public Access' enabled | D38: 3 Storage | E38: Level 1 | F38: Automated | G38: s3_account_level_public_access_blocks | H38: S3 account-level Block Public Access ignores public ACLs and restricts public buckets | I38: s3 | J38: AwsS3AccountPublicAccessBlock | K38: storage | L38: high | M38: Absent these settings, public ACLs and broad bucket policies may grant internet or cross-account access. This risks: - Confidentiality: bulk data exfiltration - Integrity: object overwrite/tampering - Availability: malicious deletions or malware hosting, triggering takedowns | N38: Block Public Access is not configured for the account {s3control_client.audited_account}. | O38: Block Public Access is configured for the account {s3control_client.audited_account}. | P38: # Terraform: Enable required S3 Account-level Block Public Access settings resource "aws_s3_account_public_access_block" "<example_resource_name>" { ignore_public_acls = true # Critical: Ignores any public ACLs account-wide restrict_public_buckets = true # Critical: Restricts buckets with public policies to same-account principals } | Q38: aws s3control put-public-access-block --account-id <account_id> --public-access-block-configuration IgnorePublicAcls=true,RestrictPublicBuckets=true | R38: https://docs.aws.amazon.com/AmazonS3/latest/userguide/access-control-block-public-access.html | S38: https://github.com/prowler-cloud/prowler/blob/master/prowler/providers/aws/services/s3/s3_account_level_public_access_blocks/s3_account_level_public_access_blocks.py | T38: =IF(OR(L38="critical",AND(L38="high",OR(K38="IAM",K38="network"))),"T3",IF(OR(L38="high",L38="medium"),"T2","T1")) -> T2
A39: P-038 | B39: 3.2.1 | C39: Ensure that encryption-at-rest is enabled for RDS instances | D39: 3 Storage | E39: Level 1 | F39: Automated | G39: rds_instance_storage_encrypted | H39: RDS DB instance storage is encrypted at rest | I39: rds | J39: AwsRdsDbInstance | K39: database | L39: high | M39: Without encryption at rest, database files, snapshots, and automated backups remain in plaintext. An attacker with access to copied snapshots, compromised backups, or underlying storage can read sensitive data, causing loss of confidentiality and enabling large-scale exfiltration. | N39: RDS Instance {db_instance.id} is not encrypted. | O39: RDS Instance {db_instance.id} is encrypted. | P39: # Terraform: create an encrypted RDS DB instance resource "aws_db_instance" "<example_resource_name>" { engine = "<engine>" instance_class = "<instance_class>" username = "<username>" password = "<password>" allocated_storage = 20 storage_encrypted = true # CRITICAL: enables encryption at rest to pass the check } | R39: https://aws.amazon.com/blogs/storage/protecting-amazon-rds-db-instances-encrypted-using-kms-aws-managed-key-with-cross-account-and-cross-region-backups/ https://docs.aws.amazon.com/AmazonRDS/latest/UserGuide/Overview.Encryption.html | S39: https://github.com/prowler-cloud/prowler/blob/master/prowler/providers/aws/services/rds/rds_instance_storage_encrypted/rds_instance_storage_encrypted.py | T39: =IF(OR(L39="critical",AND(L39="high",OR(K39="IAM",K39="network"))),"T3",IF(OR(L39="high",L39="medium"),"T2","T1")) -> T2
A40: P-039 | B40: 3.2.2 | C40: Ensure the Auto Minor Version Upgrade feature is enabled for RDS instances | D40: 3 Storage | E40: Level 1 | F40: Automated | G40: rds_instance_minor_version_upgrade_enabled | H40: RDS instance has minor version upgrade enabled | I40: rds | J40: AwsRdsDbInstance | K40: database | L40: medium | M40: Without automatic minor upgrades, databases miss security patches, leaving known vulnerabilities exploitable and risking unauthorized data access. Unapplied fixes can cause data corruption and outages, harming integrity and availability. | N40: RDS Instance {db_instance.id} does not have minor version upgrade enabled. | O40: RDS Instance {db_instance.id} has minor version upgrade enabled. | P40: # Enable auto minor version upgrades on an RDS instance resource "aws_db_instance" "<example_resource_name>" { allocated_storage = 20 engine = "mysql" instance_class = "db.t3.micro" username = "<username>" password = "<password>" auto_minor_version_upgrade = true # Critical: turns on automatic minor engine upgrades } | Q40: aws rds modify-db-instance --db-instance-identifier <db_instance_id> --auto-minor-version-upgrade --apply-immediately | R40: https://aws.amazon.com/blogs/database/best-practices-for-upgrading-amazon-rds-to-major-and-minor-versions-of-postgresql/ | S40: https://github.com/prowler-cloud/prowler/blob/master/prowler/providers/aws/services/rds/rds_instance_minor_version_upgrade_enabled/rds_instance_minor_version_upgrade_enabled.py | T40: =IF(OR(L40="critical",AND(L40="high",OR(K40="IAM",K40="network"))),"T3",IF(OR(L40="high",L40="medium"),"T2","T1")) -> T2
A41: P-040 | B41: 3.2.3 | C41: Ensure that RDS instances are not publicly accessible | D41: 3 Storage | E41: Level 1 | F41: Automated | G41: rds_instance_no_public_access | H41: RDS instance is not publicly exposed to the Internet | I41: rds | J41: AwsRdsDbInstance | K41: database | L41: critical | M41: An internet-reachable database invites: - Brute-force and vulnerability probing, risking availability and integrity - Unauthorized queries and dumps leading to confidentiality loss Compromise can enable lateral movement and persistence within the VPC. | N41: RDS Instance {db_instance.id} is set as publicly accessible and security group {security_group.name} ({security_group.id}) has {db_instance.engine} port {db_instance_port} open to the Internet at endpoint {db_instance.endpoint.get('Address')} in a public subnet {subnet_id}. | O41: RDS Instance {db_instance.id} is not publicly accessible. | P41: # Ensure the RDS instance is not publicly accessible resource "aws_db_instance" "<example_resource_name>" { publicly_accessible = false # CRITICAL: disables public access (no public endpoint) } | Q41: aws rds modify-db-instance --db-instance-identifier <db_instance_id> --no-publicly-accessible --apply-immediately | R41: https://docs.aws.amazon.com/config/latest/developerguide/rds-instance-public-access-check.html https://docs.aws.amazon.com/securityhub/latest/userguide/rds-controls.html | S41: https://github.com/prowler-cloud/prowler/blob/master/prowler/providers/aws/services/rds/rds_instance_no_public_access/rds_instance_no_public_access.py | T41: =IF(OR(L41="critical",AND(L41="high",OR(K41="IAM",K41="network"))),"T3",IF(OR(L41="high",L41="medium"),"T2","T1")) -> T3
A42: P-041 | B42: 3.2.4 | C42: Ensure Multi-AZ deployments are used for enhanced availability in Amazon RDS | D42: 3 Storage | E42: Level 1 | F42: Manual | G42: rds_cluster_multi_az | H42: RDS cluster has Multi-AZ enabled | I42: rds | J42: AwsRdsDbCluster | K42: database | L42: medium | M42: A single-AZ cluster is a single point of failure. AZ outages, instance/storage faults, or maintenance can cause extended downtime, failed transactions, and worse RTO/RPO. Without cross-AZ replicas, recovery may require restores, increasing outage duration and risking service disruption and data consistency impacts. | N42: RDS Cluster {db_cluster.id} does not have multi-AZ enabled. | O42: RDS Cluster {db_cluster.id} has multi-AZ enabled. | P42: # Terraform: create an RDS Multi-AZ DB cluster (non-Aurora) resource "aws_rds_cluster" "<example_resource_name>" { cluster_identifier = "<example_resource_id>" engine = "mysql" # CRITICAL: mysql/postgres with the lines below creates a Multi-AZ DB cluster db_cluster_instance_class = "db.r6g.large" # CRITICAL: makes this a Multi-AZ DB cluster (1 writer + 2 readers across AZs) storage_type = "io1" # CRITICAL: required for Multi-AZ DB clusters allocated_storage = 100 # CRITICAL: required for Multi-AZ DB clusters iops = 1000 # CRITICAL: required for Multi-AZ DB clusters master_username = "<USERNAME>" master_password = "<PASSWORD>" } | R42: https://docs.aws.amazon.com/securityhub/latest/userguide/rds-controls.html#rds-15 https://aws.amazon.com/rds/features/multi-az/ | S42: https://github.com/prowler-cloud/prowler/blob/master/prowler/providers/aws/services/rds/rds_cluster_multi_az/rds_cluster_multi_az.py | T42: =IF(OR(L42="critical",AND(L42="high",OR(K42="IAM",K42="network"))),"T3",IF(OR(L42="high",L42="medium"),"T2","T1")) -> T2
A43: P-042 | B43: 3.2.4 | C43: Ensure Multi-AZ deployments are used for enhanced availability in Amazon RDS | D43: 3 Storage | E43: Level 1 | F43: Manual | G43: rds_instance_multi_az | H43: RDS instance has Multi-AZ enabled | I43: rds | J43: AwsRdsDbInstance | K43: database | L43: medium | M43: Without Multi-AZ, an Availability Zone or instance failure can cause extended downtime and rely on restores, risking loss of recent writes. This degrades availability and may affect integrity, interrupting applications and breaching SLAs. | N43: RDS Instance {db_instance.id} does not have multi-AZ enabled at cluster {db_instance.cluster_id} level. | O43: RDS Instance {db_instance.id} has multi-AZ enabled at cluster {db_instance.cluster_id} level. | P43: # Enable Multi-AZ on an RDS DB instance resource "aws_db_instance" "example" { multi_az = true # Critical: enables Multi-AZ to pass the check } | Q43: aws rds modify-db-instance --db-instance-identifier <db_instance_id> --multi-az --apply-immediately | R43: https://aws.amazon.com/rds/features/multi-az/ | S43: https://github.com/prowler-cloud/prowler/blob/master/prowler/providers/aws/services/rds/rds_instance_multi_az/rds_instance_multi_az.py | T43: =IF(OR(L43="critical",AND(L43="high",OR(K43="IAM",K43="network"))),"T3",IF(OR(L43="high",L43="medium"),"T2","T1")) -> T2
A44: P-043 | B44: 3.3.1 | C44: Ensure that encryption is enabled for EFS file systems | D44: 3 Storage | E44: Level 1 | F44: Automated | G44: efs_encryption_at_rest_enabled | H44: EFS file system has encryption at rest enabled | I44: efs | J44: AwsEfsFileSystem | K44: storage | L44: medium | M44: Without encryption at rest, EFS contents can be read from storage media, backups, or compromised hosts, eroding confidentiality and enabling offline exfiltration. Privileged compromise also allows covert data harvesting or manipulation, threatening integrity of files. | N44: EFS {fs.id} does not have encryption at rest enabled. | O44: EFS {fs.id} has encryption at rest enabled. | P44: # Terraform: Create an EFS file system with encryption at rest enabled resource "aws_efs_file_system" "<example_resource_name>" { encrypted = true # Critical: enables encryption at rest so the check passes } | R44: https://docs.aws.amazon.com/efs/latest/ug/EFSKMS.html https://docs.aws.amazon.com/efs/latest/ug/encryption-at-rest.html | S44: https://github.com/prowler-cloud/prowler/blob/master/prowler/providers/aws/services/efs/efs_encryption_at_rest_enabled/efs_encryption_at_rest_enabled.py | T44: =IF(OR(L44="critical",AND(L44="high",OR(K44="IAM",K44="network"))),"T3",IF(OR(L44="high",L44="medium"),"T2","T1")) -> T2
A45: P-044 | B45: 4.1 | C45: Ensure CloudTrail is enabled in all regions | D45: 4 Logging | E45: Level 1 | F45: Manual | G45: cloudtrail_multi_region_enabled | H45: Region has at least one CloudTrail trail logging | I45: cloudtrail | J45: AwsCloudTrailTrail | K45: monitoring | L45: high | M45: Missing coverage in any region creates visibility gaps. Attackers can use lesser-monitored regions to run API actions, hide unauthorized changes, and exfiltrate data without audit trails, weakening detective controls, hindering forensics, and delaying response (confidentiality and integrity). | N45: No CloudTrail trails enabled with logging were found. | O45: Trail {trail.name} is multiregion and it is logging. | P45: # Terraform: Multi-region CloudTrail with logging enabled resource "aws_cloudtrail" "<example_resource_name>" { name = "<example_resource_name>" s3_bucket_name = "<example_resource_name>" is_multi_region_trail = true # Critical: applies the trail to all regions enable_logging = true # Critical: ensures the trail is logging } | R45: https://docs.aws.amazon.com/awscloudtrail/latest/userguide/cloudtrailconcepts.html#cloudtrail-concepts-management-events | S45: https://github.com/prowler-cloud/prowler/blob/master/prowler/providers/aws/services/cloudtrail/cloudtrail_multi_region_enabled/cloudtrail_multi_region_enabled.py | T45: =IF(OR(L45="critical",AND(L45="high",OR(K45="IAM",K45="network"))),"T3",IF(OR(L45="high",L45="medium"),"T2","T1")) -> T2
A46: P-045 | B46: 4.2 | C46: Ensure CloudTrail log file validation is enabled | D46: 4 Logging | E46: Level 2 | F46: Automated | G46: cloudtrail_log_file_validation_enabled | H46: CloudTrail trail has log file validation enabled | I46: cloudtrail | J46: AwsCloudTrailTrail | K46: monitoring | L46: medium | M46: Without validation, adversaries can alter, forge, or delete audit entries without detection, compromising log integrity and non-repudiation. This impairs investigations, enables alert evasion, and obscures unauthorized changes across regions or accounts. | N46: Multiregion trail {trail.name} has log file validation disabled. | O46: Multiregion trail {trail.name} has log file validation enabled. | P46: # Enable log file validation on a CloudTrail trail resource "aws_cloudtrail" "<example_resource_name>" { name = "<example_resource_name>" s3_bucket_name = "<example_resource_name>" enable_log_file_validation = true # Critical: ensures CloudTrail writes signed digests to detect tampering } | Q46: aws cloudtrail update-trail --name <trail_name> --enable-log-file-validation | R46: https://docs.aws.amazon.com/awscloudtrail/latest/userguide/cloudtrail-log-file-validation-intro.html https://docs.aws.amazon.com/awscloudtrail/latest/userguide/cloudtrail-log-file-validation-enabling.html | S46: https://github.com/prowler-cloud/prowler/blob/master/prowler/providers/aws/services/cloudtrail/cloudtrail_log_file_validation_enabled/cloudtrail_log_file_validation_enabled.py | T46: =IF(OR(L46="critical",AND(L46="high",OR(K46="IAM",K46="network"))),"T3",IF(OR(L46="high",L46="medium"),"T2","T1")) -> T2
A47: P-046 | B47: 4.3 | C47: Ensure AWS Config is enabled in all regions | D47: 4 Logging | E47: Level 2 | F47: Automated | G47: config_recorder_all_regions_enabled | H47: AWS Config recorder is enabled and not in failure state or disabled | I47: config | J47: Other | K47: monitoring | L47: medium | M47: Gaps in Config recording create blind spots. Changes in unmonitored Regions aren't captured, weakening integrity and auditability. Adversaries can alter resources or stage assets unnoticed, enabling misconfigurations and delaying incident response. | N47: No AWS Config recorders in region. | O47: AWS Config recorder {recorder.name} is enabled. | P47: resource "aws_iam_service_linked_role" "example_resource" { aws_service_name = "config.amazonaws.com" } resource "aws_config_configuration_recorder" "example_resource" { name = "example_resource" role_arn = aws_iam_service_linked_role.example_resource.arn } resource "aws_config_delivery_channel" "example_resource" { s3_bucket_name = "example_resource" } resource "aws_config_configuration_recorder_status" "example_resource" { name = aws_config_configuration_recorder.example_resource.name is_recording = true # This line fixes the security issue depends_on = [aws_config_delivery_channel.example_resource] } | R47: https://aws.amazon.com/blogs/mt/aws-config-best-practices/ | S47: https://github.com/prowler-cloud/prowler/blob/master/prowler/providers/aws/services/config/config_recorder_all_regions_enabled/config_recorder_all_regions_enabled.py | T47: =IF(OR(L47="critical",AND(L47="high",OR(K47="IAM",K47="network"))),"T3",IF(OR(L47="high",L47="medium"),"T2","T1")) -> T2
A48: P-047 | B48: 4.4 | C48: Ensure that server access logging is enabled on the CloudTrail S3 bucket | D48: 4 Logging | E48: Level 1 | F48: Manual | G48: cloudtrail_logs_s3_bucket_access_logging_enabled | H48: CloudTrail trail destination S3 bucket has access logging enabled | I48: cloudtrail | J48: AwsCloudTrailTrail | K48: monitoring | L48: medium | M48: Without access logging on the CloudTrail logs bucket, access and changes to log files lack an independent audit trail. Attackers could read, delete, or replace logs without attribution, undermining log confidentiality and integrity, and slowing incident response. | N48: Multiregion Trail {trail.name} S3 bucket access logging is not enabled for bucket {trail_bucket}. | O48: Multiregion Trail {trail.name} S3 bucket access logging is enabled for bucket {trail_bucket}. | P48: # Enable access logging on the CloudTrail S3 bucket resource "aws_s3_bucket" "<example_log_bucket_name>" { bucket = "<example_log_bucket_name>" } resource "aws_s3_bucket" "<example_bucket_name>" { bucket = "<example_bucket_name>" } resource "aws_s3_bucket_logging" "<example_resource_name>" { bucket = aws_s3_bucket.<example_bucket_name>.id target_bucket = aws_s3_bucket.<example_log_bucket_name>.id # Critical: enables server access logging to the target bucket } | Q48: aws s3api put-bucket-logging --bucket <CLOUDTRAIL_BUCKET_NAME> --bucket-logging-status "{\"LoggingEnabled\":{\"TargetBucket\":\"<TARGET_BUCKET_NAME>\"}}" | R48: https://docs.aws.amazon.com/securityhub/latest/userguide/cloudtrail-controls.html https://docs.aws.amazon.com/AmazonS3/latest/dev/security-best-practices.html | S48: https://github.com/prowler-cloud/prowler/blob/master/prowler/providers/aws/services/cloudtrail/cloudtrail_logs_s3_bucket_access_logging_enabled/cloudtrail_logs_s3_bucket_access_logging_enabled.py | T48: =IF(OR(L48="critical",AND(L48="high",OR(K48="IAM",K48="network"))),"T3",IF(OR(L48="high",L48="medium"),"T2","T1")) -> T2
A49: P-048 | B49: 4.5 | C49: Ensure CloudTrail logs are encrypted at rest using KMS CMKs | D49: 4 Logging | E49: Level 2 | F49: Automated | G49: cloudtrail_kms_encryption_enabled | H49: CloudTrail trail logs are encrypted at rest with a KMS key | I49: cloudtrail | J49: AwsCloudTrailTrail | K49: monitoring | L49: medium | M49: Absent a customer-managed KMS key, log protection relies only on storage permissions. Bucket misconfigurations or stolen credentials can expose audit data, aiding evasion and lateral movement. Missing key-level controls, rotation, and usage audit weaken confidentiality and forensic integrity. | N49: Multiregion trail {trail.name} has encryption disabled. | O49: Multiregion trail {trail.name} has encryption enabled. | P49: # Enable KMS encryption for CloudTrail resource "aws_cloudtrail" "<example_resource_name>" { name = "<example_resource_name>" s3_bucket_name = "<example_resource_name>" kms_key_id = "<example_resource_id>" # Critical: uses this KMS key to encrypt CloudTrail logs } | Q49: aws cloudtrail update-trail --name <trail_name> --kms-key-id <kms_key_arn_or_id> | R49: https://docs.aws.amazon.com/awscloudtrail/latest/userguide/encrypting-cloudtrail-log-files-with-aws-kms.html | S49: https://github.com/prowler-cloud/prowler/blob/master/prowler/providers/aws/services/cloudtrail/cloudtrail_kms_encryption_enabled/cloudtrail_kms_encryption_enabled.py | T49: =IF(OR(L49="critical",AND(L49="high",OR(K49="IAM",K49="network"))),"T3",IF(OR(L49="high",L49="medium"),"T2","T1")) -> T2
A50: P-049 | B50: 4.6 | C50: Ensure rotation for customer-created symmetric CMKs is enabled | D50: 4 Logging | E50: Level 2 | F50: Automated | G50: kms_cmk_rotation_enabled | H50: KMS customer-managed symmetric CMK has automatic rotation enabled | I50: kms | J50: AwsKmsKey | K50: security | L50: high | M50: Without automatic rotation, long-lived key material increases confidentiality and integrity risk. If a KMS key is exposed, attackers can unwrap data keys and decrypt stored data until the key changes. It also reduces crypto agility and may conflict with mandated rotation policies. | N50: KMS CMK {key.id} has automatic rotation disabled. | O50: KMS CMK {key.id} has automatic rotation enabled. | P50: # KMS key with automatic rotation enabled resource "aws_kms_key" "<example_resource_name>" { enable_key_rotation = true # Critical: enables automatic rotation so the key passes the check } | Q50: aws kms enable-key-rotation --key-id <KEY_ID> | R50: https://docs.aws.amazon.com/kms/latest/developerguide/rotate-keys.html https://aws.amazon.com/blogs/security/how-to-get-ready-for-certificate-transparency/ | S50: https://github.com/prowler-cloud/prowler/blob/master/prowler/providers/aws/services/kms/kms_cmk_rotation_enabled/kms_cmk_rotation_enabled.py | T50: =IF(OR(L50="critical",AND(L50="high",OR(K50="IAM",K50="network"))),"T3",IF(OR(L50="high",L50="medium"),"T2","T1")) -> T2
A51: P-050 | B51: 4.7 | C51: Ensure VPC flow logging is enabled in all VPCs | D51: 4 Logging | E51: Level 2 | F51: Automated | G51: vpc_flow_logs_enabled | H51: VPC flow logs are enabled | I51: vpc | J51: AwsEc2Vpc | K51: network | L51: medium | M51: Without flow logs, network activity is opaque, hindering detection and investigation of malicious traffic. Attackers can probe, exfiltrate, or move laterally unnoticed, impacting confidentiality and integrity; outages and misconfigurations are harder to diagnose, reducing availability. | N51: VPC {vpc.name if vpc.name else vpc.id} Flow logs are disabled. | O51: VPC {vpc.name if vpc.name else vpc.id} Flow logs are enabled. | P51: # Enable VPC Flow Logs to S3 for an existing VPC resource "aws_flow_log" "vpc" { vpc_id = "<example_resource_id>" # Critical: target the VPC to enable flow logs traffic_type = "ALL" # Critical: log all traffic log_destination_type = "s3" # Critical: send logs to S3 (no IAM role needed) log_destination = "arn:aws:s3:::<example_resource_name>" # Critical: S3 bucket ARN } | Q51: aws ec2 create-flow-logs --resource-type VPC --resource-ids <VPC_ID> --traffic-type ALL --log-destination-type s3 --log-destination arn:aws:s3:::<S3_BUCKET_NAME> | R51: http://docs.aws.amazon.com/AmazonVPC/latest/UserGuide/flow-logs.html | S51: https://github.com/prowler-cloud/prowler/blob/master/prowler/providers/aws/services/vpc/vpc_flow_logs_enabled/vpc_flow_logs_enabled.py | T51: =IF(OR(L51="critical",AND(L51="high",OR(K51="IAM",K51="network"))),"T3",IF(OR(L51="high",L51="medium"),"T2","T1")) -> T2
A52: P-051 | B52: 4.8 | C52: Ensure that object-level logging for write events is enabled for S3 buckets | D52: 4 Logging | E52: Level 2 | F52: Automated | G52: cloudtrail_s3_dataevents_write_enabled | H52: CloudTrail trail records all S3 object-level API operations for all buckets | I52: cloudtrail | J52: AwsCloudTrailTrail | K52: monitoring | L52: low | M52: Without object-level write logging, unauthorized or accidental changes and deletions can go unobserved, undermining data integrity and availability. Forensics lose visibility into who modified or removed objects, hindering detection of ransomware, rogue automation, or insider tampering. | N52: No CloudTrail trails have a data event to record all S3 object-level API operations. | O52: Trail {trail.name} from home region {trail.home_region} has a classic data event selector to record all S3 object-level API operations. | P52: resource "aws_cloudtrail" "<example_resource_name>" { name = "<example_resource_name>" s3_bucket_name = "<example_resource_name>" event_selector { read_write_type = "WriteOnly" data_resource { type = "AWS::S3::Object" values = ["arn:aws:s3"] # Critical: logs S3 object-level write events for all buckets to pass the check } } } | Q52: aws cloudtrail put-event-selectors --trail-name <example_resource_name> --event-selectors '[{"ReadWriteType":"WriteOnly","DataResources":[{"Type":"AWS::S3::Object","Values":["arn:aws:s3"]}]}]' | R52: https://docs.aws.amazon.com/awscloudtrail/latest/userguide/logging-data-events-with-cloudtrail.html https://docs.aws.amazon.com/AmazonS3/latest/userguide/enable-cloudtrail-logging-for-s3.html https://docs.aws.amazon.com/securityhub/latest/userguide/s3-controls.html#s3-22 | S52: https://github.com/prowler-cloud/prowler/blob/master/prowler/providers/aws/services/cloudtrail/cloudtrail_s3_dataevents_write_enabled/cloudtrail_s3_dataevents_write_enabled.py | T52: =IF(OR(L52="critical",AND(L52="high",OR(K52="IAM",K52="network"))),"T3",IF(OR(L52="high",L52="medium"),"T2","T1")) -> T1
A53: P-052 | B53: 4.9 | C53: Ensure that object-level logging for read events is enabled for S3 buckets | D53: 4 Logging | E53: Level 2 | F53: Automated | G53: cloudtrail_s3_dataevents_read_enabled | H53: CloudTrail trail records S3 object-level read events for all S3 buckets | I53: cloudtrail | J53: AwsCloudTrailTrail | K53: monitoring | L53: low | M53: Without object-level read logging, S3 access is opaque. Attackers or insiders can exfiltrate data via GetObject without audit trails, eroding confidentiality and hindering forensics, anomaly detection, and incident response. | N53: No CloudTrail trails have a data event to record all S3 object-level API operations. | O53: Trail {trail.name} from home region {trail.home_region} has a classic data event selector to record all S3 object-level API operations. | P53: # Terraform: enable S3 object-level READ data events for all buckets on a trail resource "aws_cloudtrail" "<example_resource_name>" { name = "<example_resource_name>" s3_bucket_name = "<example_resource_name>" event_selector { read_write_type = "ReadOnly" # CRITICAL: log read-only data events data_resource { type = "AWS::S3::Object" # CRITICAL: target S3 object-level events values = ["arn:aws:s3"] # CRITICAL: apply to all S3 buckets/objects } } } | Q53: aws cloudtrail put-event-selectors --trail-name <example_resource_name> --event-selectors '[{"ReadWriteType":"ReadOnly","DataResources":[{"Type":"AWS::S3::Object","Values":["arn:aws:s3"]}]}]' | R53: https://docs.aws.amazon.com/securityhub/latest/userguide/s3-controls.html#s3-23 https://docs.aws.amazon.com/AmazonS3/latest/userguide/enable-cloudtrail-logging-for-s3.html | S53: https://github.com/prowler-cloud/prowler/blob/master/prowler/providers/aws/services/cloudtrail/cloudtrail_s3_dataevents_read_enabled/cloudtrail_s3_dataevents_read_enabled.py | T53: =IF(OR(L53="critical",AND(L53="high",OR(K53="IAM",K53="network"))),"T3",IF(OR(L53="high",L53="medium"),"T2","T1")) -> T1
A54: P-053 | B54: 4.10 | C54: Ensure all AWS-managed web front-end services have access logging enabled | D54: 4 Logging | E54: Level 1 | F54: Manual | G54: cloudfront_distributions_logging_enabled | H54: CloudFront distribution has logging enabled | I54: cloudfront | J54: AwsCloudFrontDistribution | K54: network | L54: medium | M54: Missing CloudFront logs blinds monitoring of edge requests, impeding detection of bot abuse, credential stuffing, and cache-bypass attempts. This delays incident response and weakens forensic evidence. A delivery source without an active delivery does not count as enabled. | N54: CloudFront Distribution {distribution.id} has logging disabled. | O54: CloudFront Distribution {distribution.id} has logging enabled via {', '.join(methods)}. | P54: # Add this block to your existing CloudFront distribution to enable access logging resource "aws_cloudfront_distribution" "<example_resource_name>" { # ... existing required config ... logging_config { bucket = "<example_bucket>.s3.amazonaws.com" # CRITICAL: enables standard access logs to S3 } } | Q54: aws cloudfront get-distribution-config --id <DISTRIBUTION_ID> --output json > current-config.json && echo 'Manually edit current-config.json to add Logging.Bucket: <example_bucket>.s3.amazonaws.com', then run:' && echo 'aws cloudfront update-distribution --id <DISTRIBUTION_ID> --distribution-config file://current-config.json --if-match $(aws cloudfront get-distribution-config --id <DISTRIBUTION_ID> --query "ETag" --output text)' | R54: https://docs.aws.amazon.com/AmazonCloudFront/latest/DeveloperGuide/AccessLogs.html https://aws.amazon.com/awstv/watch/e895e7811ac/ https://docs.aws.amazon.com/AmazonCloudFront/latest/DeveloperGuide/real-time-logs.html | S54: https://github.com/prowler-cloud/prowler/blob/master/prowler/providers/aws/services/cloudfront/cloudfront_distributions_logging_enabled/cloudfront_distributions_logging_enabled.py | T54: =IF(OR(L54="critical",AND(L54="high",OR(K54="IAM",K54="network"))),"T3",IF(OR(L54="high",L54="medium"),"T2","T1")) -> T2
A55: P-054 | B55: 4.10 | C55: Ensure all AWS-managed web front-end services have access logging enabled | D55: 4 Logging | E55: Level 1 | F55: Manual | G55: elbv2_logging_enabled | H55: ELBv2 Application Load Balancer has access logs to S3 configured | I55: elbv2 | J55: AwsElbv2LoadBalancer | K55: network | L55: medium | M55: Absent ALB access logs reduces visibility and hampers incident detection and forensics. Malicious requests, credential stuffing, or data exfiltration via the load balancer can go unnoticed, undermining confidentiality and integrity, and delaying recovery from availability incidents. | N55: ELBv2 ALB {lb.name} does not have access logs configured. | O55: ELBv2 ALB {lb.name} has access logs to S3 configured. | P55: # Terraform: enable ALB access logs to S3 resource "aws_lb" "<example_resource_name>" { name = "<example_resource_name>" security_groups = ["<example_security_group_id>"] subnets = ["<subnet_id_1>", "<subnet_id_2>"] access_logs { bucket = "<example_resource_name>" # critical: destination S3 bucket for logs enabled = true # critical: enable ALB access logging } } | Q55: aws elbv2 modify-load-balancer-attributes --load-balancer-arn <lb_arn> --attributes Key=access_logs.s3.enabled,Value=true Key=access_logs.s3.bucket,Value=<bucket_name> | R55: https://docs.aws.amazon.com/elasticloadbalancing/latest/application/load-balancer-access-logs.html | S55: https://github.com/prowler-cloud/prowler/blob/master/prowler/providers/aws/services/elbv2/elbv2_logging_enabled/elbv2_logging_enabled.py | T55: =IF(OR(L55="critical",AND(L55="high",OR(K55="IAM",K55="network"))),"T3",IF(OR(L55="high",L55="medium"),"T2","T1")) -> T2
A56: P-055 | B56: 4.10 | C56: Ensure all AWS-managed web front-end services have access logging enabled | D56: 4 Logging | E56: Level 1 | F56: Manual | G56: apigateway_restapi_logging_enabled | H56: API Gateway REST API stage has logging enabled | I56: apigateway | J56: AwsApiGatewayStage | K56: api_gateway | L56: medium | M56: Without stage logging, API activity lacks visibility, hindering detection of abuse and incident response. Attackers can probe endpoints, exfiltrate data, or tamper integrations without traces, impacting confidentiality, integrity, and availability and blocking forensic investigation. | N56: API Gateway {rest_api.name} ID {rest_api.id} in stage {stage.name} has logging disabled. | O56: API Gateway {rest_api.name} ID {rest_api.id} in stage {stage.name} has logging enabled. | P56: # Enable execution logging for all methods in a REST API stage resource "aws_api_gateway_method_settings" "<example_resource_name>" { rest_api_id = "<example_resource_id>" stage_name = "<example_resource_name>" method_path = "/" settings { logging_level = "ERROR" # CRITICAL: enables stage execution logging } } | Q56: aws apigateway update-stage --rest-api-id <REST_API_ID> --stage-name <STAGE_NAME> --patch-operations op=replace,path='///logging/loglevel',value=ERROR | R56: https://docs.aws.amazon.com/apigateway/latest/developerguide/security-monitoring.html https://docs.aws.amazon.com/apigateway/latest/developerguide/http-api-logging.html https://docs.aws.amazon.com/apigateway/latest/developerguide/set-up-logging.html https://docs.aws.amazon.com/apigateway/latest/developerguide/view-cloudwatch-log-events-in-cloudwatch-console.html | S56: https://github.com/prowler-cloud/prowler/blob/master/prowler/providers/aws/services/apigateway/apigateway_restapi_logging_enabled/apigateway_restapi_logging_enabled.py | T56: =IF(OR(L56="critical",AND(L56="high",OR(K56="IAM",K56="network"))),"T3",IF(OR(L56="high",L56="medium"),"T2","T1")) -> T2
A57: P-056 | B57: 4.10 | C57: Ensure all AWS-managed web front-end services have access logging enabled | D57: 4 Logging | E57: Level 1 | F57: Manual | G57: apigatewayv2_api_access_logging_enabled | H57: API Gateway V2 API stage has access logging enabled | I57: apigatewayv2 | J57: AwsApiGatewayV2Stage | K57: api_gateway | L57: medium | M57: Without access logs, API calls lack traceability, making it hard to spot credential misuse, route abuse, or anomalous traffic. This reduces confidentiality and integrity through undetected data access or manipulation, and impacts availability by slowing incident response. | N57: API Gateway V2 {api.name} ID {api.id} in stage {stage.name} has access logging disabled. | O57: API Gateway V2 {api.name} ID {api.id} in stage {stage.name} has access logging enabled. | P57: # Terraform: Enable access logging on API Gateway V2 stage resource "aws_apigatewayv2_stage" "<example_resource_name>" { api_id = "<example_resource_id>" name = "<example_resource_name>" access_log_settings { # Critical: enables access logging for the stage destination_arn = "<example_log_group_arn>" format = "{\"requestId\":\"$context.requestId\"}" } } | Q57: aws apigatewayv2 update-stage --api-id <API_ID> --stage-name <STAGE_NAME> --access-log-settings DestinationArn=<LOG_GROUP_ARN>,Format='{"requestId":"$context.requestId"}' | R57: https://docs.aws.amazon.com/apigateway/latest/developerguide/security-monitoring.html https://docs.aws.amazon.com/apigateway/latest/developerguide/set-up-logging.html | S57: https://github.com/prowler-cloud/prowler/blob/master/prowler/providers/aws/services/apigatewayv2/apigatewayv2_api_access_logging_enabled/apigatewayv2_api_access_logging_enabled.py | T57: =IF(OR(L57="critical",AND(L57="high",OR(K57="IAM",K57="network"))),"T3",IF(OR(L57="high",L57="medium"),"T2","T1")) -> T2
A58: P-057 | B58: 5.1 | C58: Ensure unauthorized API calls are monitored | D58: 5 Monitoring | E58: Level 2 | F58: Manual | G58: cloudwatch_log_metric_filter_unauthorized_api_calls | H58: CloudWatch Logs metric filter and alarm exist for unauthorized API calls | I58: cloudwatch | J58: AwsCloudWatchAlarm | K58: monitoring | L58: medium | M58: Without alerting on unauthorized API calls, permission probing and failed access by compromised identities can go unnoticed. Attackers can enumerate services, pivot, and attempt privilege escalation, threatening data confidentiality and integrity. | N58: No CloudWatch log groups found with metric filters or alarms associated. | P58: # Terraform: Metric filter and alarm for unauthorized API calls resource "aws_cloudwatch_log_metric_filter" "unauthorized" { name = "unauthorized_api_calls_metric" log_group_name = "<example_resource_name>" pattern = "{($.errorCode = \"UnauthorizedOperation\") || ($.errorCode = \"AccessDenied\")}" # Critical: detects unauthorized/denied API calls metric_transformation { name = "unauthorized_api_calls_metric" namespace = "CISBenchmark" value = "1" } } resource "aws_cloudwatch_metric_alarm" "unauthorized" { comparison_operator = "GreaterThanOrEqualToThreshold" evaluation_periods = 1 metric_name = "unauthorized_api_calls_metric" # Critical: alarm on the metric from the filter namespace = "CISBenchmark" period = 300 statistic = "Sum" threshold = 1 } | R58: https://docs.aws.amazon.com/awscloudtrail/latest/userguide/cloudwatch-alarms-for-cloudtrail.html | S58: https://github.com/prowler-cloud/prowler/blob/master/prowler/providers/aws/services/cloudwatch/cloudwatch_log_metric_filter_unauthorized_api_calls/cloudwatch_log_metric_filter_unauthorized_api_calls.py | T58: =IF(OR(L58="critical",AND(L58="high",OR(K58="IAM",K58="network"))),"T3",IF(OR(L58="high",L58="medium"),"T2","T1")) -> T2
A59: P-058 | B59: 5.2 | C59: Ensure management console sign-in without MFA is monitored | D59: 5 Monitoring | E59: Level 1 | F59: Manual | G59: cloudwatch_log_metric_filter_sign_in_without_mfa | H59: CloudWatch log metric filter and alarm exist for Management Console sign-in without MFA | I59: cloudwatch | J59: AwsCloudWatchAlarm | K59: monitoring | L59: medium | M59: Without alerting on non-MFA console logins, successful use of stolen passwords can go undetected, enabling: - Unauthorized console access and IAM changes - Data exfiltration or deletion Impacts: loss of confidentiality and integrity, and potential availability disruption. | N59: No CloudWatch log groups found with metric filters or alarms associated. | P59: # Create metric filter for console sign-in without MFA resource "aws_cloudwatch_log_metric_filter" "nomfa" { name = "<example_resource_name>" log_group_name = "<example_resource_name>" pattern = "{ ($.eventName = \"ConsoleLogin\") && ($.additionalEventData.MFAUsed != \"Yes\") }" # CRITICAL: detects ConsoleLogin without MFA metric_transformation { name = "<example_resource_name>" namespace = "<example_resource_name>" value = "1" # CRITICAL: emits a count per match } } # Alarm on the emitted metric resource "aws_cloudwatch_metric_alarm" "nomfa" { alarm_name = "<example_resource_name>" metric_name = aws_cloudwatch_log_metric_filter.nomfa.metric_transformation[0].name # CRITICAL: ties alarm to the metric namespace = aws_cloudwatch_log_metric_filter.nomfa.metric_transformation[0].namespace comparison_operator = "GreaterThanOrEqualToThreshold" evaluation_periods = 1 period = 300 statistic = "Sum" threshold = 1 # CRITICAL: alarm on first event } | R59: https://docs.aws.amazon.com/awscloudtrail/latest/userguide/cloudwatch-alarms-for-cloudtrail.html | S59: https://github.com/prowler-cloud/prowler/blob/master/prowler/providers/aws/services/cloudwatch/cloudwatch_log_metric_filter_sign_in_without_mfa/cloudwatch_log_metric_filter_sign_in_without_mfa.py | T59: =IF(OR(L59="critical",AND(L59="high",OR(K59="IAM",K59="network"))),"T3",IF(OR(L59="high",L59="medium"),"T2","T1")) -> T2
A60: P-059 | B60: 5.3 | C60: Ensure usage of the 'root' account is monitored | D60: 5 Monitoring | E60: Level 1 | F60: Manual | G60: cloudwatch_log_metric_filter_root_usage | H60: Account has a CloudWatch Logs metric filter and alarm for root account usage | I60: cloudwatch | J60: AwsCloudWatchAlarm | K60: monitoring | L60: medium | M60: Without alerting on root activity, full-privilege actions can proceed unnoticed, impacting: - confidentiality via data access/exfiltration - integrity via policy/config tampering - availability via deletions or shutdowns Delayed detection increases blast radius and persistence. | N60: No CloudWatch log groups found with metric filters or alarms associated. | P60: # CloudWatch Logs metric filter for root account usage resource "aws_cloudwatch_log_metric_filter" "<example_resource_name>" { name = "<example_resource_name>" log_group_name = "<example_resource_name>" pattern = "{ $.userIdentity.type = \"Root\" && $.userIdentity.invokedBy NOT EXISTS && $.eventType != \"AwsServiceEvent\" }" # CRITICAL: detects root user actions metric_transformation { name = "<example_resource_name>" # CRITICAL: metric used by the alarm namespace = "<example_resource_name>" value = "1" } } # Alarm on the root usage metric resource "aws_cloudwatch_metric_alarm" "<example_resource_name>" { comparison_operator = "GreaterThanOrEqualToThreshold" evaluation_periods = 1 metric_name = "<example_resource_name>" # CRITICAL: matches metric filter namespace = "<example_resource_name>" period = 300 statistic = "Sum" threshold = 1 } | R60: https://docs.aws.amazon.com/awscloudtrail/latest/userguide/cloudwatch-alarms-for-cloudtrail.html https://aws.amazon.com/blogs/security/how-to-receive-notifications-when-your-aws-accounts-root-access-keys-are-used/ | S60: https://github.com/prowler-cloud/prowler/blob/master/prowler/providers/aws/services/cloudwatch/cloudwatch_log_metric_filter_root_usage/cloudwatch_log_metric_filter_root_usage.py | T60: =IF(OR(L60="critical",AND(L60="high",OR(K60="IAM",K60="network"))),"T3",IF(OR(L60="high",L60="medium"),"T2","T1")) -> T2
A61: P-060 | B61: 5.4 | C61: Ensure IAM policy changes are monitored | D61: 5 Monitoring | E61: Level 1 | F61: Manual | G61: cloudwatch_log_metric_filter_policy_changes | H61: CloudWatch Logs metric filter and alarm exist for IAM policy changes | I61: cloudwatch | J61: AwsCloudWatchAlarm | K61: monitoring | L61: medium | M61: Absent alerting on IAM policy changes, privilege modifications can go unnoticed, enabling privilege escalation, hidden backdoors, or permission revocations. This threatens confidentiality and integrity, and may impact availability if critical access is removed or misconfigured. | N61: No CloudWatch log groups found with metric filters or alarms associated. | P61: # Terraform: Metric filter and alarm for IAM policy changes resource "aws_cloudwatch_log_metric_filter" "<example_resource_name>" { name = "<example_resource_name>" log_group_name = "<example_resource_name>" # CloudTrail log group # CRITICAL: Pattern matching IAM policy change events required by the check pattern = "{($.eventName=DeleteGroupPolicy)||($.eventName=DeleteRolePolicy)||($.eventName=DeleteUserPolicy)||($.eventName=PutGroupPolicy)||($.eventName=PutRolePolicy)||($.eventName=PutUserPolicy)||($.eventName=CreatePolicy)||($.eventName=DeletePolicy)||($.eventName=CreatePolicyVersion)||($.eventName=DeletePolicyVersion)||($.eventName=AttachRolePolicy)||($.eventName=DetachRolePolicy)||($.eventName=AttachUserPolicy)||($.eventName=DetachUserPolicy)||($.eventName=AttachGroupPolicy)||($.eventName=DetachGroupPolicy)}" metric_transformation { name = "<example_resource_name>" # CRITICAL: Metric created from filter namespace = "CISBenchmark" # CRITICAL: Namespace for the metric value = "1" } } resource "aws_cloudwatch_metric_alarm" "<example_resource_name>" { alarm_name = "<example_resource_name>" # CRITICAL: Alarm on the metric when >= 1 event occurs metric_name = aws_cloudwatch_log_metric_filter.<example_resource_name>.metric_transformation[0].name namespace = aws_cloudwatch_log_metric_filter.<example_resource_name>.metric_transformation[0].namespace statistic = "Sum" period = 300 evaluation_periods = 1 threshold = 1 comparison_operator = "GreaterThanOrEqualToThreshold" } | R61: https://docs.aws.amazon.com/awscloudtrail/latest/userguide/cloudwatch-alarms-for-cloudtrail.html | S61: https://github.com/prowler-cloud/prowler/blob/master/prowler/providers/aws/services/cloudwatch/cloudwatch_log_metric_filter_policy_changes/cloudwatch_log_metric_filter_policy_changes.py | T61: =IF(OR(L61="critical",AND(L61="high",OR(K61="IAM",K61="network"))),"T3",IF(OR(L61="high",L61="medium"),"T2","T1")) -> T2
A62: P-061 | B62: 5.5 | C62: Ensure CloudTrail configuration changes are monitored | D62: 5 Monitoring | E62: Level 1 | F62: Manual | G62: cloudwatch_log_metric_filter_and_alarm_for_cloudtrail_configuration_changes_enabled | H62: CloudWatch Logs metric filter and alarm exist for CloudTrail configuration changes | I62: cloudwatch | J62: AwsCloudWatchAlarm | K62: monitoring | L62: medium | M62: Absent this monitoring, logging can be stopped or altered without notice, eroding visibility. That enables covert activity and data exfiltration without audit evidence, harming confidentiality, the integrity of records, and the availability of reliable logs for detection and forensics. | N62: No CloudWatch log groups found with metric filters or alarms associated. | P62: resource "aws_cloudwatch_log_metric_filter" "cfg" { name = "<example_resource_name>" log_group_name = "<example_resource_name>" # CRITICAL: CloudTrail log group pattern = "{($.eventName = CreateTrail) || ($.eventName = UpdateTrail) || ($.eventName = DeleteTrail) || ($.eventName = StartLogging) || ($.eventName = StopLogging)}" # CRITICAL: Detects CloudTrail config changes metric_transformation { name = "<example_resource_name>" # CRITICAL: Metric created by filter namespace = "<example_resource_name>" value = "1" } } resource "aws_cloudwatch_metric_alarm" "cfg" { metric_name = "<example_resource_name>" # CRITICAL: Uses metric from filter namespace = "<example_resource_name>" comparison_operator = "GreaterThanOrEqualToThreshold" evaluation_periods = 1 period = 300 statistic = "Sum" threshold = 1 } | R62: https://docs.aws.amazon.com/awscloudtrail/latest/userguide/cloudwatch-alarms-for-cloudtrail.html | S62: https://github.com/prowler-cloud/prowler/blob/master/prowler/providers/aws/services/cloudwatch/cloudwatch_log_metric_filter_and_alarm_for_cloudtrail_configuration_changes_enabled/cloudwatch_log_metric_filter_and_alarm_for_cloudtrail_configuration_changes_enabled.py | T62: =IF(OR(L62="critical",AND(L62="high",OR(K62="IAM",K62="network"))),"T3",IF(OR(L62="high",L62="medium"),"T2","T1")) -> T2
A63: P-062 | B63: 5.6 | C63: Ensure AWS Management Console authentication failures are monitored | D63: 5 Monitoring | E63: Level 2 | F63: Manual | G63: cloudwatch_log_metric_filter_authentication_failures | H63: Account has a CloudWatch Logs metric filter and alarm for AWS Management Console authentication failures | I63: cloudwatch | J63: AwsCloudWatchAlarm | K63: monitoring | L63: medium | M63: Absent visibility into failed console logins enables undetected brute-force and credential-stuffing attempts, extending attacker dwell time. Successful guesses can grant console access, risking data confidentiality, configuration integrity, and availability through destructive changes. | N63: No CloudWatch log groups found with metric filters or alarms associated. | P63: # Metric filter and alarm for console authentication failures resource "aws_cloudwatch_log_metric_filter" "metric" { name = "<example_resource_name>" log_group_name = "<example_resource_name>" pattern = "{($.eventName = ConsoleLogin) && ($.errorMessage = \"Failed authentication\") }" # Critical: detects failed console logins metric_transformation { name = "<example_resource_name>" # Critical: metric created by filter namespace = "<example_resource_name>" # Critical: metric namespace value = "1" } } resource "aws_cloudwatch_metric_alarm" "alarm" { metric_name = aws_cloudwatch_log_metric_filter.metric.metric_transformation[0].name # Critical: alarm references the filter's metric namespace = aws_cloudwatch_log_metric_filter.metric.metric_transformation[0].namespace # Critical: must match comparison_operator = "GreaterThanOrEqualToThreshold" evaluation_periods = 1 period = 300 statistic = "Sum" threshold = 1 } | R63: https://docs.aws.amazon.com/awscloudtrail/latest/userguide/cloudwatch-alarms-for-cloudtrail.html | S63: https://github.com/prowler-cloud/prowler/blob/master/prowler/providers/aws/services/cloudwatch/cloudwatch_log_metric_filter_authentication_failures/cloudwatch_log_metric_filter_authentication_failures.py | T63: =IF(OR(L63="critical",AND(L63="high",OR(K63="IAM",K63="network"))),"T3",IF(OR(L63="high",L63="medium"),"T2","T1")) -> T2
A64: P-063 | B64: 5.7 | C64: Ensure disabling or scheduled deletion of customer created CMKs is monitored | D64: 5 Monitoring | E64: Level 2 | F64: Manual | G64: cloudwatch_log_metric_filter_disable_or_scheduled_deletion_of_kms_cmk | H64: Account has a CloudWatch log metric filter and alarm for disabling or scheduled deletion of customer-managed KMS keys | I64: cloudwatch | J64: AwsCloudWatchAlarm | K64: monitoring | L64: medium | M64: Missing alerts on CMK disablement or scheduled deletion undermines availability and integrity: encrypted data may become undecryptable, backups unusable, and recovery impossible. Attackers or insiders can change key states unnoticed, causing outages and irreversible data loss. | N64: No CloudWatch log groups found with metric filters or alarms associated. | P64: # Metric filter for KMS DisableKey or ScheduleKeyDeletion resource "aws_cloudwatch_log_metric_filter" "cmk" { name = "<example_resource_name>" log_group_name = "<example_resource_name>" # CRITICAL: CloudTrail log group # CRITICAL: Detect KMS key disable or scheduled deletion events pattern = "{($.eventSource = kms.amazonaws.com) && (($.eventName=DisableKey)||($.eventName=ScheduleKeyDeletion)) }" metric_transformation { name = "disable_or_delete_cmk_changes_metric" # CRITICAL: metric used by alarm namespace = "CISBenchmark" value = "1" } } # Alarm for the metric above resource "aws_cloudwatch_metric_alarm" "cmk" { alarm_name = "<example_resource_name>" comparison_operator = "GreaterThanOrEqualToThreshold" evaluation_periods = 1 metric_name = "disable_or_delete_cmk_changes_metric" # CRITICAL: same metric name namespace = "CISBenchmark" period = 300 statistic = "Sum" threshold = 1 } | R64: https://docs.aws.amazon.com/kms/latest/developerguide/deleting-keys-creating-cloudwatch-alarm.html | S64: https://github.com/prowler-cloud/prowler/blob/master/prowler/providers/aws/services/cloudwatch/cloudwatch_log_metric_filter_disable_or_scheduled_deletion_of_kms_cmk/cloudwatch_log_metric_filter_disable_or_scheduled_deletion_of_kms_cmk.py | T64: =IF(OR(L64="critical",AND(L64="high",OR(K64="IAM",K64="network"))),"T3",IF(OR(L64="high",L64="medium"),"T2","T1")) -> T2
A65: P-064 | B65: 5.8 | C65: Ensure S3 bucket policy changes are monitored | D65: 5 Monitoring | E65: Level 1 | F65: Manual | G65: cloudwatch_log_metric_filter_for_s3_bucket_policy_changes | H65: CloudWatch log metric filter and alarm exist for S3 bucket policy changes | I65: cloudwatch | J65: AwsCloudWatchAlarm | K65: monitoring | L65: medium | M65: Without alerting on S3 policy and ACL changes, unauthorized modifications can go unnoticed, weakening confidentiality and integrity. Misuse could expose buckets publicly, grant write/delete access, or alter replication paths, enabling data exfiltration and destructive actions. | N65: No CloudWatch log groups found with metric filters or alarms associated. | P65: # CloudWatch metric filter for S3 bucket policy changes resource "aws_cloudwatch_log_metric_filter" "<example_resource_name>" { name = "<example_resource_name>" log_group_name = "<example_resource_name>" # Critical: detects S3 bucket policy changes from CloudTrail logs pattern = "{($.eventSource=s3.amazonaws.com) && (($.eventName=PutBucketAcl) || ($.eventName=PutBucketPolicy) || ($.eventName=PutBucketCors) || ($.eventName=PutBucketLifecycle) || ($.eventName=PutBucketReplication) || ($.eventName=DeleteBucketPolicy) || ($.eventName=DeleteBucketCors) || ($.eventName=DeleteBucketLifecycle) || ($.eventName=DeleteBucketReplication))}" metric_transformation { name = "<example_resource_name>" namespace = "<example_resource_name>" value = "1" } } # Alarm on the metric filter resource "aws_cloudwatch_metric_alarm" "<example_resource_name>" { alarm_name = "<example_resource_name>" metric_name = "<example_resource_name>" # Critical: matches metric filter namespace = "<example_resource_name>" # Critical: matches metric filter comparison_operator = "GreaterThanOrEqualToThreshold" evaluation_periods = 1 period = 300 statistic = "Sum" threshold = 1 } | R65: https://docs.aws.amazon.com/awscloudtrail/latest/userguide/cloudwatch-alarms-for-cloudtrail.html | S65: https://github.com/prowler-cloud/prowler/blob/master/prowler/providers/aws/services/cloudwatch/cloudwatch_log_metric_filter_for_s3_bucket_policy_changes/cloudwatch_log_metric_filter_for_s3_bucket_policy_changes.py | T65: =IF(OR(L65="critical",AND(L65="high",OR(K65="IAM",K65="network"))),"T3",IF(OR(L65="high",L65="medium"),"T2","T1")) -> T2
A66: P-065 | B66: 5.9 | C66: Ensure AWS Config configuration changes are monitored | D66: 5 Monitoring | E66: Level 2 | F66: Manual | G66: cloudwatch_log_metric_filter_and_alarm_for_aws_config_configuration_changes_enabled | H66: CloudWatch Logs metric filter and alarm exist for AWS Config configuration changes | I66: cloudwatch | J66: AwsCloudWatchAlarm | K66: monitoring | L66: medium | M66: Without alerting on AWS Config changes, actions like StopConfigurationRecorder or DeleteDeliveryChannel can silently suspend recording and delivery. This degrades the integrity and availability of configuration audit data, enabling undetected changes and delaying incident response. | N66: No CloudWatch log groups found with metric filters or alarms associated. | P66: # CloudWatch Logs metric filter for AWS Config changes resource "aws_cloudwatch_log_metric_filter" "config_change" { name = "aws_config_changes_metric" log_group_name = "<example_resource_name>" pattern = "{($.eventSource = config.amazonaws.com) && (($.eventName=StopConfigurationRecorder)||($.eventName=DeleteDeliveryChannel)||($.eventName=PutDeliveryChannel)||($.eventName=PutConfigurationRecorder))}" # Critical: detects AWS Config configuration change events metric_transformation { name = "aws_config_changes_metric" # Critical: metric used by the alarm namespace = "CISBenchmark" value = "1" } } # Alarm for the above metric resource "aws_cloudwatch_metric_alarm" "config_change" { alarm_name = "aws_config_changes_alarm" metric_name = "aws_config_changes_metric" # Critical: ties alarm to the metric filter namespace = "CISBenchmark" comparison_operator = "GreaterThanOrEqualToThreshold" evaluation_periods = 1 period = 300 statistic = "Sum" threshold = 1 # Critical: alarm on first occurrence } | R66: https://docs.aws.amazon.com/awscloudtrail/latest/userguide/cloudwatch-alarms-for-cloudtrail.html | S66: https://github.com/prowler-cloud/prowler/blob/master/prowler/providers/aws/services/cloudwatch/cloudwatch_log_metric_filter_and_alarm_for_aws_config_configuration_changes_enabled/cloudwatch_log_metric_filter_and_alarm_for_aws_config_configuration_changes_enabled.py | T66: =IF(OR(L66="critical",AND(L66="high",OR(K66="IAM",K66="network"))),"T3",IF(OR(L66="high",L66="medium"),"T2","T1")) -> T2
A67: P-066 | B67: 5.10 | C67: Ensure security group changes are monitored | D67: 5 Monitoring | E67: Level 2 | F67: Manual | G67: cloudwatch_log_metric_filter_security_group_changes | H67: CloudWatch Logs metric filter and alarm exist for security group changes | I67: cloudwatch | J67: AwsCloudWatchAlarm | K67: monitoring | L67: medium | M67: Without alerting on security group changes, unauthorized or mistaken rules can expose services to the Internet, enabling brute force and lateral movement (confidentiality, integrity). Deletions or restrictive edits can break connectivity (availability). Delayed detection increases attacker dwell time and impact. | N67: No CloudWatch log groups found with metric filters or alarms associated. | P67: # Metric filter for Security Group changes resource "aws_cloudwatch_log_metric_filter" "sg" { name = "<example_resource_name>" log_group_name = "<example_log_group_name>" # Critical: Matches Security Group change events required by the check pattern = "{ ($.eventName = AuthorizeSecurityGroupIngress) || ($.eventName = AuthorizeSecurityGroupEgress) || ($.eventName = RevokeSecurityGroupIngress) || ($.eventName = RevokeSecurityGroupEgress) || ($.eventName = CreateSecurityGroup) || ($.eventName = DeleteSecurityGroup) }" metric_transformation { name = "<example_metric_name>" namespace = "<example_metric_namespace>" value = "1" } } # Alarm for the above metric resource "aws_cloudwatch_metric_alarm" "sg" { alarm_name = "<example_resource_name>" # Critical: Alarm on the SG change metric to pass the control metric_name = "<example_metric_name>" namespace = "<example_metric_namespace>" statistic = "Sum" period = 300 evaluation_periods = 1 threshold = 1 comparison_operator = "GreaterThanOrEqualToThreshold" } | R67: https://docs.aws.amazon.com/awscloudtrail/latest/userguide/cloudwatch-alarms-for-cloudtrail.html https://docs.aws.amazon.com/AmazonCloudWatch/latest/monitoring/Alarm-On-Logs.html | S67: https://github.com/prowler-cloud/prowler/blob/master/prowler/providers/aws/services/cloudwatch/cloudwatch_log_metric_filter_security_group_changes/cloudwatch_log_metric_filter_security_group_changes.py | T67: =IF(OR(L67="critical",AND(L67="high",OR(K67="IAM",K67="network"))),"T3",IF(OR(L67="high",L67="medium"),"T2","T1")) -> T2
A68: P-067 | B68: 5.11 | C68: Ensure Network Access Control List (NACL) changes are monitored | D68: 5 Monitoring | E68: Level 2 | F68: Manual | G68: cloudwatch_changes_to_network_acls_alarm_configured | H68: CloudWatch log metric filter and alarm exist for Network ACL (NACL) change events | I68: cloudwatch | J68: AwsCloudWatchAlarm | K68: monitoring | L68: medium | M68: Absent monitoring of NACL changes reduces detection of policy tampering, risking loss of confidentiality (opened ingress/egress), degraded network integrity (lateral movement, bypassed segmentation), and reduced availability (traffic blackholes or lockouts). | N68: No CloudWatch log groups found with metric filters or alarms associated. | P68: # CloudWatch metric filter and alarm for NACL changes resource "aws_cloudwatch_log_metric_filter" "nacl" { name = "nacl_changes" log_group_name = "<example_resource_name>" # CloudTrail log group pattern = "{ ($.eventName = CreateNetworkAcl) || ($.eventName = CreateNetworkAclEntry) || ($.eventName = DeleteNetworkAcl) || ($.eventName = DeleteNetworkAclEntry) || ($.eventName = ReplaceNetworkAclEntry) || ($.eventName = ReplaceNetworkAclAssociation) }" # CRITICAL: detects NACL changes metric_transformation { name = "nacl_changes" namespace = "CISBenchmark" value = "1" } } resource "aws_cloudwatch_metric_alarm" "nacl" { alarm_name = "nacl_changes" comparison_operator = "GreaterThanOrEqualToThreshold" evaluation_periods = 1 metric_name = "nacl_changes" # CRITICAL: alarm targets the metric from the filter namespace = "CISBenchmark" period = 300 statistic = "Sum" threshold = 1 } | R68: https://docs.aws.amazon.com/awscloudtrail/latest/userguide/cloudwatch-alarms-for-cloudtrail.html | S68: https://github.com/prowler-cloud/prowler/blob/master/prowler/providers/aws/services/cloudwatch/cloudwatch_changes_to_network_acls_alarm_configured/cloudwatch_changes_to_network_acls_alarm_configured.py | T68: =IF(OR(L68="critical",AND(L68="high",OR(K68="IAM",K68="network"))),"T3",IF(OR(L68="high",L68="medium"),"T2","T1")) -> T2
A69: P-068 | B69: 5.12 | C69: Ensure changes to network gateways are monitored | D69: 5 Monitoring | E69: Level 1 | F69: Manual | G69: cloudwatch_changes_to_network_gateways_alarm_configured | H69: CloudWatch Logs metric filter and alarm exist for changes to network gateways | I69: cloudwatch | J69: AwsCloudWatchAlarm | K69: monitoring | L69: medium | M69: Without this monitoring, gateway changes can expose private networks to the Internet or break connectivity. Adversaries or mistakes can enable data exfiltration, bypass network inspection, and trigger outages via deletions or detachments, impacting confidentiality and availability. | N69: No CloudWatch log groups found with metric filters or alarms associated. | P69: # CloudWatch Logs metric filter for network gateway changes resource "aws_cloudwatch_log_metric_filter" "<example_resource_name>" { name = "<example_resource_name>" log_group_name = "<example_resource_name>" pattern = "{ ($.eventName = CreateCustomerGateway) || ($.eventName = DeleteCustomerGateway) || ($.eventName = AttachInternetGateway) || ($.eventName = CreateInternetGateway) || ($.eventName = DeleteInternetGateway) || ($.eventName = DetachInternetGateway) }" # Critical: matches gateway change events metric_transformation { name = "<example_resource_name>" namespace = "<example_resource_name>" value = "1" } } # Alarm on the metric filter resource "aws_cloudwatch_metric_alarm" "<example_resource_name>" { alarm_name = "<example_resource_name>" comparison_operator = "GreaterThanOrEqualToThreshold" evaluation_periods = 1 metric_name = "<example_resource_name>" # Critical: must match metric from the filter namespace = "<example_resource_name>" period = 300 statistic = "Sum" threshold = 1 } | R69: https://docs.aws.amazon.com/awscloudtrail/latest/userguide/cloudwatch-alarms-for-cloudtrail.html https://docs.aws.amazon.com/securityhub/latest/userguide/cloudwatch-controls.html#cloudwatch-12 | S69: https://github.com/prowler-cloud/prowler/blob/master/prowler/providers/aws/services/cloudwatch/cloudwatch_changes_to_network_gateways_alarm_configured/cloudwatch_changes_to_network_gateways_alarm_configured.py | T69: =IF(OR(L69="critical",AND(L69="high",OR(K69="IAM",K69="network"))),"T3",IF(OR(L69="high",L69="medium"),"T2","T1")) -> T2
... A72: P-071 | B72: 5.15 | C72: Ensure AWS Organizations changes are monitored | D72: 5 Monitoring | E72: Level 1 | F72: Manual | G72: cloudwatch_log_metric_filter_aws_organizations_changes | H72: CloudWatch Logs metric filter and alarm exist for AWS Organizations changes | I72: cloudwatch | J72: AwsCloudWatchAlarm | K72: monitoring | L72: medium | M72: Without alerting on AWS Organizations changes, attackers or misconfigurations can silently alter governance, enabling unauthorized access and policy bypass. They could create/remove accounts, change or detach SCPs, or delete the organization, risking data exposure (C), privilege escalation (I), and service disruption (A). | N72: No CloudWatch log groups found with metric filters or alarms associated. | P72: # CloudWatch Logs metric filter for AWS Organizations changes resource "aws_cloudwatch_log_metric_filter" "organizations_changes" { name = "<example_resource_name>" log_group_name = "<example_log_group_name>" pattern = "{ ($.eventSource = organizations.amazonaws.com) && (($.eventName = \"AcceptHandshake\") || ($.eventName = \"AttachPolicy\") || ($.eventName = \"CancelHandshake\") || ($.eventName = \"CreateAccount\") || ($.eventName = \"CreateOrganization\") || ($.eventName = \"CreateOrganizationalUnit\") || ($.eventName = \"CreatePolicy\") || ($.eventName = \"DeclineHandshake\") || ($.eventName = \"DeleteOrganization\") || ($.eventName = \"DeleteOrganizationalUnit\") || ($.eventName = \"DeletePolicy\") || ($.eventName = \"EnableAllFeatures\") || ($.eventName = \"EnablePolicyType\") || ($.eventName = \"InviteAccountToOrganization\") || ($.eventName = \"LeaveOrganization\") || ($.eventName = \"DetachPolicy\") || ($.eventName = \"DisablePolicyType\") || ($.eventName = \"MoveAccount\") || ($.eventName = \"RemoveAccountFromOrganization\") || ($.eventName = \"UpdateOrganizationalUnit\") || ($.eventName = \"UpdatePolicy\")) }" # Critical: matches AWS Organizations change events metric_transformation { name = "<example_resource_name>" # Critical: metric created by the filter namespace = "CISBenchmark" # Critical: used by the alarm value = "1" } } # Alarm on the metric generated by the filter resource "aws_cloudwatch_metric_alarm" "organizations_changes" { alarm_name = "<example_resource_name>" comparison_operator = "GreaterThanOrEqualToThreshold" evaluation_periods = 1 metric_name = "<example_resource_name>" # Critical: matches metric filter name namespace = "CISBenchmark" # Critical: matches metric filter namespace period = 300 statistic = "Sum" threshold = 1 } | R72: https://docs.aws.amazon.com/awscloudtrail/latest/userguide/cloudwatch-alarms-for-cloudtrail.html | S72: https://github.com/prowler-cloud/prowler/blob/master/prowler/providers/aws/services/cloudwatch/cloudwatch_log_metric_filter_aws_organizations_changes/cloudwatch_log_metric_filter_aws_organizations_changes.py | T72: =IF(OR(L72="critical",AND(L72="high",OR(K72="IAM",K72="network"))),"T3",IF(OR(L72="high",L72="medium"),"T2","T1")) -> T2
A73: P-072 | B73: 5.16 | C73: Ensure AWS Security Hub is enabled | D73: 5 Monitoring | E73: Level 2 | F73: Automated | G73: securityhub_enabled | H73: Security Hub is enabled with standards or integrations configured | I73: securityhub | J73: Other | K73: security | L73: high | M73: Absent Security Hub coverage or standards, security signals are fragmented and control checks don't run. High-risk findings can be missed or delayed, enabling data exfiltration, persistence, and lateral movement. This reduces visibility and undermines confidentiality, integrity, and availability across accounts/Regions. | N73: Security Hub is enabled but without any standard or integration. | O73: Security Hub is enabled with standards: {securityhub.standards}. | P73: # Enable Security Hub resource "aws_securityhub_account" "<example_resource_name>" {} # Critical: Enable at least one standard so the check passes resource "aws_securityhub_standards_subscription" "<example_resource_name>_fsbp" { standards_arn = "arn:aws:securityhub:<REGION>::standards/aws-foundational-security-best-practices/v/1.0.0" # Enables AWS FSBP } | R73: https://docs.aws.amazon.com/securityhub/latest/userguide/securityhub-settingup.html https://docs.aws.amazon.com/securityhub/latest/userguide/securityhub-standards-enable-disable.html | S73: https://github.com/prowler-cloud/prowler/blob/master/prowler/providers/aws/services/securityhub/securityhub_enabled/securityhub_enabled.py | T73: =IF(OR(L73="critical",AND(L73="high",OR(K73="IAM",K73="network"))),"T3",IF(OR(L73="high",L73="medium"),"T2","T1")) -> T2
A74: P-073 | B74: 6.1.1 | C74: Ensure EBS volume encryption is enabled in all regions | D74: 6 Networking | E74: Level 1 | F74: Automated | G74: ec2_ebs_default_encryption | H74: EBS default encryption is enabled | I74: ec2 | J74: AwsEc2Volume | K74: compute | L74: high | M74: Without encryption by default, data on new EBS volumes and snapshots may be stored in plaintext. A compromised account or mis-shared snapshot can expose disk contents, enabling data exfiltration, offline analysis, and loss of confidentiality. | N74: EBS Default Encryption is not activated. | O74: EBS Default Encryption is activated. | P74: resource "aws_ebs_encryption_by_default" "<example_resource_name>" { enabled = true # Critical: enables default EBS encryption in this region } | Q74: aws ec2 enable-ebs-encryption-by-default --region <REGION> | R74: https://aws.amazon.com/premiumsupport/knowledge-center/ebs-automatic-encryption/ https://docs.aws.amazon.com/ebs/latest/userguide/encryption-by-default.html | S74: https://github.com/prowler-cloud/prowler/blob/master/prowler/providers/aws/services/ec2/ec2_ebs_default_encryption/ec2_ebs_default_encryption.py | T74: =IF(OR(L74="critical",AND(L74="high",OR(K74="IAM",K74="network"))),"T3",IF(OR(L74="high",L74="medium"),"T2","T1")) -> T2
A75: P-074 | B75: 6.1.2 | C75: Ensure CIFS access is restricted to trusted networks to prevent unauthorized access | D75: 6 Networking | E75: Level 1 | F75: Automated | G75: ec2_instance_port_cifs_exposed_to_internet | H75: EC2 instance does not allow Internet ingress to TCP ports 139 or 445 (CIFS) | I75: ec2 | J75: AwsEc2Instance | K75: compute | L75: critical | M75: Publicly reachable SMB allows unauthorized access and remote code execution, enabling credential theft, NTLM relay, and share enumeration. Attackers can exfiltrate files, tamper or delete data, and spread ransomware, degrading confidentiality, integrity, and availability. | O75: Instance {instance.id} does not have CIFS ports open to the Internet. | P75: # Security group without CIFS open to the Internet resource "aws_security_group" "<example_resource_name>" { name = "<example_resource_name>" vpc_id = "<example_resource_id>" ingress { from_port = 139 to_port = 139 protocol = "tcp" cidr_blocks = ["10.0.0.0/8"] # CRITICAL: restrict CIFS (139); do not use 0.0.0.0/0 } ingress { from_port = 445 to_port = 445 protocol = "tcp" cidr_blocks = ["10.0.0.0/8"] # CRITICAL: restrict CIFS (445); do not use 0.0.0.0/0 } } | Q75: aws ec2 revoke-security-group-ingress --group-id <SECURITY_GROUP_ID> --ip-permissions '[{"IpProtocol":"tcp","FromPort":139,"ToPort":139,"IpRanges":[{"CidrIp":"0.0.0.0/0"}]},{"IpProtocol":"tcp","FromPort":445,"ToPort":445,"IpRanges":[{"CidrIp":"0.0.0.0/0"}]}]' | R75: https://docs.aws.amazon.com/vpc/latest/userguide/VPC_SecurityGroups.html | S75: https://github.com/prowler-cloud/prowler/blob/master/prowler/providers/aws/services/ec2/ec2_instance_port_cifs_exposed_to_internet/ec2_instance_port_cifs_exposed_to_internet.py | T75: =IF(OR(L75="critical",AND(L75="high",OR(K75="IAM",K75="network"))),"T3",IF(OR(L75="high",L75="medium"),"T2","T1")) -> T3
A76: P-075 | B76: 6.2 | C76: Ensure no Network ACLs allow ingress from 0.0.0.0/0 to remote server administration ports | D76: 6 Networking | E76: Level 1 | F76: Automated | G76: ec2_networkacl_allow_ingress_any_port | H76: Network ACL does not allow ingress from 0.0.0.0/0 to any port | I76: ec2 | J76: AwsEc2NetworkAcl | K76: network | L76: high | M76: Allowing Internet-wide ingress at the subnet layer enables broad port scanning and unsolicited connections. Attackers can probe and exploit exposed services, risking data disclosure and tampering (confidentiality, integrity) and causing outages via floods or brute-force (availability). Any security group lapse then lacks a compensating control. | N76: Network ACL {network_acl.name if network_acl.name else network_acl.id} has every port open to the Internet. | O76: Network ACL {network_acl.name if network_acl.name else network_acl.id} does not have every port open to the Internet. | P76: # Deny all inbound from the Internet on the NACL resource "aws_network_acl_rule" "<example_resource_name>" { network_acl_id = "<example_resource_id>" rule_number = 100 egress = false protocol = "-1" rule_action = "deny" # CRITICAL: Denies ingress cidr_block = "0.0.0.0/0" # CRITICAL: From the Internet (any IP) } | Q76: aws ec2 replace-network-acl-entry --network-acl-id <example_resource_id> --ingress --rule-number <RULE_NUMBER> --protocol -1 --rule-action deny --cidr-block 0.0.0.0/0 | R76: https://docs.aws.amazon.com/vpc/latest/userguide/vpc-network-acls.html | S76: https://github.com/prowler-cloud/prowler/blob/master/prowler/providers/aws/services/ec2/ec2_networkacl_allow_ingress_any_port/ec2_networkacl_allow_ingress_any_port.py | T76: =IF(OR(L76="critical",AND(L76="high",OR(K76="IAM",K76="network"))),"T3",IF(OR(L76="high",L76="medium"),"T2","T1")) -> T3
A77: P-076 | B77: 6.2 | C77: Ensure no Network ACLs allow ingress from 0.0.0.0/0 to remote server administration ports | D77: 6 Networking | E77: Level 1 | F77: Automated | G77: ec2_networkacl_allow_ingress_tcp_port_22 | H77: Network ACL does not allow ingress from the Internet to TCP port 22 (SSH) | I77: ec2 | J77: AwsEc2NetworkAcl | K77: network | L77: medium | M77: An ACL allowing Internet-wide SSH erodes defense in depth. Systems reachable on TCP 22 face brute-force, credential stuffing, reconnaissance, and SSH exploit attempts. Changes to routes or security groups can create direct exposure, enabling unauthorized access and lateral movement, undermining confidentiality and integrity. | N77: Network ACL {network_acl.name if network_acl.name else network_acl.id} has SSH port 22 open to the Internet. | O77: Network ACL {network_acl.name if network_acl.name else network_acl.id} does not have SSH port 22 open to the Internet. | P77: # Deny SSH (22) from Internet on the NACL resource "aws_network_acl_rule" "<example_resource_name>" { network_acl_id = "<example_resource_id>" rule_number = 1 egress = false protocol = "tcp" rule_action = "deny" # Critical: blocks SSH ingress cidr_block = "0.0.0.0/0" # Critical: Internet sources from_port = 22 # Critical: SSH port to_port = 22 } | Q77: aws ec2 replace-network-acl-entry --network-acl-id <NETWORK_ACL_ID> --ingress --rule-number <RULE_NUMBER> --protocol 6 --rule-action deny --cidr-block 0.0.0.0/0 --port-range From=22,To=22 | R77: https://docs.aws.amazon.com/vpc/latest/userguide/vpc-network-acls.html | S77: https://github.com/prowler-cloud/prowler/blob/master/prowler/providers/aws/services/ec2/ec2_networkacl_allow_ingress_tcp_port_22/ec2_networkacl_allow_ingress_tcp_port_22.py | T77: =IF(OR(L77="critical",AND(L77="high",OR(K77="IAM",K77="network"))),"T3",IF(OR(L77="high",L77="medium"),"T2","T1")) -> T2
A78: P-077 | B78: 6.2 | C78: Ensure no Network ACLs allow ingress from 0.0.0.0/0 to remote server administration ports | D78: 6 Networking | E78: Level 1 | F78: Automated | G78: ec2_networkacl_allow_ingress_tcp_port_3389 | H78: Network ACL does not allow ingress from the Internet to TCP port 3389 (RDP) | I78: ec2 | J78: AwsEc2NetworkAcl | K78: network | L78: medium | M78: Internet-exposed RDP enables password spraying, brute force, and exploitation of RDP flaws to gain remote control. Allowing it at the subnet layer weakens defense in depth-a misconfigured security group or route can expose instances-leading to data exfiltration, privilege escalation, and ransomware, impacting confidentiality and integrity. | N78: Network ACL {network_acl.name if network_acl.name else network_acl.id} has Microsoft RDP port 3389 open to the Internet. | O78: Network ACL {network_acl.name if network_acl.name else network_acl.id} does not have Microsoft RDP port 3389 open to the Internet. | P78: # Deny inbound RDP (TCP 3389) from the Internet on an existing NACL resource "aws_network_acl_rule" "<example_resource_name>" { network_acl_id = "<example_resource_id>" rule_number = 1 # Critical: lower than any allow so deny takes precedence egress = false # Ingress rule protocol = "tcp" rule_action = "deny" # Critical: block the traffic cidr_block = "0.0.0.0/0" # Critical: Internet source from_port = 3389 # Critical: RDP port to_port = 3389 } | Q78: aws ec2 delete-network-acl-entry --network-acl-id <NETWORK_ACL_ID> --ingress --rule-number <RULE_NUMBER> | R78: https://docs.aws.amazon.com/vpc/latest/userguide/vpc-network-acls.html | S78: https://github.com/prowler-cloud/prowler/blob/master/prowler/providers/aws/services/ec2/ec2_networkacl_allow_ingress_tcp_port_3389/ec2_networkacl_allow_ingress_tcp_port_3389.py | T78: =IF(OR(L78="critical",AND(L78="high",OR(K78="IAM",K78="network"))),"T3",IF(OR(L78="high",L78="medium"),"T2","T1")) -> T2
A79: P-078 | B79: 6.3 | C79: Ensure no security groups allow ingress from 0.0.0.0/0 to remote server administration ports | D79: 6 Networking | E79: Level 1 | F79: Automated | G79: ec2_securitygroup_allow_ingress_from_internet_to_all_ports | H79: Security group does not have all ports open to the Internet | I79: ec2 | J79: AwsEc2SecurityGroup | K79: network | L79: critical | M79: Opening every port to the Internet enables broad scanning and exploit attempts, leading to unauthorized access, remote code execution, and data exfiltration, with easier lateral movement into the VPC. Confidentiality, integrity, and availability are all at risk. | N79: Security group {security_group.name} ({security_group.id}) has all ports open to the Internet. | O79: Security group {security_group.name} ({security_group.id}) does not have all ports open to the Internet. | P79: # Security Group with no inbound rules (prevents all ports open to the Internet) resource "aws_security_group" "<example_resource_name>" { name = "<example_resource_name>" vpc_id = "<example_resource_id>" # Critical: no ingress blocks; avoids any rule with protocol "-1" from 0.0.0.0/0 or ::/0 } | R79: https://docs.aws.amazon.com/vpc/latest/userguide/VPC_SecurityGroups.html | S79: https://github.com/prowler-cloud/prowler/blob/master/prowler/providers/aws/services/ec2/ec2_securitygroup_allow_ingress_from_internet_to_all_ports/ec2_securitygroup_allow_ingress_from_internet_to_all_ports.py | T79: =IF(OR(L79="critical",AND(L79="high",OR(K79="IAM",K79="network"))),"T3",IF(OR(L79="high",L79="medium"),"T2","T1")) -> T3
A80: P-079 | B80: 6.3 | C80: Ensure no security groups allow ingress from 0.0.0.0/0 to remote server administration ports | D80: 6 Networking | E80: Level 1 | F80: Automated | G80: ec2_securitygroup_allow_ingress_from_internet_to_tcp_port_22 | H80: Security group does not allow ingress from 0.0.0.0/0 or ::/0 to TCP port 22 (SSH) | I80: ec2 | J80: AwsEc2SecurityGroup | K80: network | L80: high | M80: Exposed SSH invites Internet-scale brute force and credential stuffing. A successful login grants remote shell, enabling data theft (confidentiality), code or config tampering (integrity), and cryptomining or service disruption (availability), plus lateral movement within the environment. | N80: Security group {security_group.name} ({security_group.id}) has SSH port 22 open to the Internet. | O80: Security group {security_group.name} ({security_group.id}) does not have SSH port 22 open to the Internet. | P80: # Terraform: restrict SSH from the Internet resource "aws_security_group" "<example_resource_name>" { vpc_id = "<example_resource_id>" ingress { from_port = 22 to_port = 22 protocol = "tcp" cidr_blocks = ["10.0.0.0/8"] # Critical: do not use 0.0.0.0/0 or ::/0 } } | Q80: aws ec2 revoke-security-group-ingress --group-id <SECURITY_GROUP_ID> --protocol tcp --port 22 --cidr 0.0.0.0/0 | R80: https://docs.aws.amazon.com/vpc/latest/userguide/VPC_SecurityGroups.html | S80: https://github.com/prowler-cloud/prowler/blob/master/prowler/providers/aws/services/ec2/ec2_securitygroup_allow_ingress_from_internet_to_tcp_port_22/ec2_securitygroup_allow_ingress_from_internet_to_tcp_port_22.py | T80: =IF(OR(L80="critical",AND(L80="high",OR(K80="IAM",K80="network"))),"T3",IF(OR(L80="high",L80="medium"),"T2","T1")) -> T3
A81: P-080 | B81: 6.3 | C81: Ensure no security groups allow ingress from 0.0.0.0/0 to remote server administration ports | D81: 6 Networking | E81: Level 1 | F81: Automated | G81: ec2_securitygroup_allow_ingress_from_internet_to_tcp_port_3389 | H81: Security group does not allow ingress from the Internet to TCP port 3389 (RDP) | I81: ec2 | J81: AwsEc2SecurityGroup | K81: network | L81: high | M81: Internet-exposed RDP enables brute force and credential stuffing and increases the chance of remote code execution via RDP flaws. Adversaries can gain interactive access, exfiltrate data (confidentiality), tamper with systems (integrity), and trigger ransomware or service disruption (availability). | N81: Security group {security_group.name} ({security_group.id}) has Microsoft RDP port 3389 open to the Internet. | O81: Security group {security_group.name} ({security_group.id}) does not have Microsoft RDP port 3389 open to the Internet. | P81: # Restrict RDP (3389) from the Internet resource "aws_security_group" "<example_resource_name>" { vpc_id = "<example_resource_id>" ingress { from_port = 3389 to_port = 3389 protocol = "tcp" cidr_blocks = ["10.0.0.0/8"] # FIX: not 0.0.0.0/0; restricts RDP to internal range } } | Q81: aws ec2 revoke-security-group-ingress --group-id <SECURITY_GROUP_ID> --protocol tcp --port 3389 --cidr 0.0.0.0/0 | R81: https://docs.aws.amazon.com/vpc/latest/userguide/VPC_SecurityGroups.html | S81: https://github.com/prowler-cloud/prowler/blob/master/prowler/providers/aws/services/ec2/ec2_securitygroup_allow_ingress_from_internet_to_tcp_port_3389/ec2_securitygroup_allow_ingress_from_internet_to_tcp_port_3389.py | T81: =IF(OR(L81="critical",AND(L81="high",OR(K81="IAM",K81="network"))),"T3",IF(OR(L81="high",L81="medium"),"T2","T1")) -> T3
A82: P-081 | B82: 6.4 | C82: Ensure no security groups allow ingress from ::/0 to remote server administration ports | D82: 6 Networking | E82: Level 1 | F82: Automated | G82: ec2_securitygroup_allow_ingress_from_internet_to_all_ports | H82: Security group does not have all ports open to the Internet | I82: ec2 | J82: AwsEc2SecurityGroup | K82: network | L82: critical | M82: Opening every port to the Internet enables broad scanning and exploit attempts, leading to unauthorized access, remote code execution, and data exfiltration, with easier lateral movement into the VPC. Confidentiality, integrity, and availability are all at risk. | N82: Security group {security_group.name} ({security_group.id}) has all ports open to the Internet. | O82: Security group {security_group.name} ({security_group.id}) does not have all ports open to the Internet. | P82: # Security Group with no inbound rules (prevents all ports open to the Internet) resource "aws_security_group" "<example_resource_name>" { name = "<example_resource_name>" vpc_id = "<example_resource_id>" # Critical: no ingress blocks; avoids any rule with protocol "-1" from 0.0.0.0/0 or ::/0 } | R82: https://docs.aws.amazon.com/vpc/latest/userguide/VPC_SecurityGroups.html | S82: https://github.com/prowler-cloud/prowler/blob/master/prowler/providers/aws/services/ec2/ec2_securitygroup_allow_ingress_from_internet_to_all_ports/ec2_securitygroup_allow_ingress_from_internet_to_all_ports.py | T82: =IF(OR(L82="critical",AND(L82="high",OR(K82="IAM",K82="network"))),"T3",IF(OR(L82="high",L82="medium"),"T2","T1")) -> T3
A83: P-082 | B83: 6.4 | C83: Ensure no security groups allow ingress from ::/0 to remote server administration ports | D83: 6 Networking | E83: Level 1 | F83: Automated | G83: ec2_securitygroup_allow_ingress_from_internet_to_tcp_port_22 | H83: Security group does not allow ingress from 0.0.0.0/0 or ::/0 to TCP port 22 (SSH) | I83: ec2 | J83: AwsEc2SecurityGroup | K83: network | L83: high | M83: Exposed SSH invites Internet-scale brute force and credential stuffing. A successful login grants remote shell, enabling data theft (confidentiality), code or config tampering (integrity), and cryptomining or service disruption (availability), plus lateral movement within the environment. | N83: Security group {security_group.name} ({security_group.id}) has SSH port 22 open to the Internet. | O83: Security group {security_group.name} ({security_group.id}) does not have SSH port 22 open to the Internet. | P83: # Terraform: restrict SSH from the Internet resource "aws_security_group" "<example_resource_name>" { vpc_id = "<example_resource_id>" ingress { from_port = 22 to_port = 22 protocol = "tcp" cidr_blocks = ["10.0.0.0/8"] # Critical: do not use 0.0.0.0/0 or ::/0 } } | Q83: aws ec2 revoke-security-group-ingress --group-id <SECURITY_GROUP_ID> --protocol tcp --port 22 --cidr 0.0.0.0/0 | R83: https://docs.aws.amazon.com/vpc/latest/userguide/VPC_SecurityGroups.html | S83: https://github.com/prowler-cloud/prowler/blob/master/prowler/providers/aws/services/ec2/ec2_securitygroup_allow_ingress_from_internet_to_tcp_port_22/ec2_securitygroup_allow_ingress_from_internet_to_tcp_port_22.py | T83: =IF(OR(L83="critical",AND(L83="high",OR(K83="IAM",K83="network"))),"T3",IF(OR(L83="high",L83="medium"),"T2","T1")) -> T3
A84: P-083 | B84: 6.4 | C84: Ensure no security groups allow ingress from ::/0 to remote server administration ports | D84: 6 Networking | E84: Level 1 | F84: Automated | G84: ec2_securitygroup_allow_ingress_from_internet_to_tcp_port_3389 | H84: Security group does not allow ingress from the Internet to TCP port 3389 (RDP) | I84: ec2 | J84: AwsEc2SecurityGroup | K84: network | L84: high | M84: Internet-exposed RDP enables brute force and credential stuffing and increases the chance of remote code execution via RDP flaws. Adversaries can gain interactive access, exfiltrate data (confidentiality), tamper with systems (integrity), and trigger ransomware or service disruption (availability). | N84: Security group {security_group.name} ({security_group.id}) has Microsoft RDP port 3389 open to the Internet. | O84: Security group {security_group.name} ({security_group.id}) does not have Microsoft RDP port 3389 open to the Internet. | P84: # Restrict RDP (3389) from the Internet resource "aws_security_group" "<example_resource_name>" { vpc_id = "<example_resource_id>" ingress { from_port = 3389 to_port = 3389 protocol = "tcp" cidr_blocks = ["10.0.0.0/8"] # FIX: not 0.0.0.0/0; restricts RDP to internal range } } | Q84: aws ec2 revoke-security-group-ingress --group-id <SECURITY_GROUP_ID> --protocol tcp --port 3389 --cidr 0.0.0.0/0 | R84: https://docs.aws.amazon.com/vpc/latest/userguide/VPC_SecurityGroups.html | S84: https://github.com/prowler-cloud/prowler/blob/master/prowler/providers/aws/services/ec2/ec2_securitygroup_allow_ingress_from_internet_to_tcp_port_3389/ec2_securitygroup_allow_ingress_from_internet_to_tcp_port_3389.py | T84: =IF(OR(L84="critical",AND(L84="high",OR(K84="IAM",K84="network"))),"T3",IF(OR(L84="high",L84="medium"),"T2","T1")) -> T3
A85: P-084 | B85: 6.5 | C85: Ensure the default security group of every VPC restricts all traffic | D85: 6 Networking | E85: Level 2 | F85: Automated | G85: ec2_securitygroup_default_restrict_traffic | H85: VPC default security group has no inbound or outbound rules | I85: ec2 | J85: AwsEc2SecurityGroup | K85: network | L85: high | M85: Permissive rules in the default security group mean instances that inherit it can communicate widely. This enables lateral movement, port scanning, and data exfiltration; unrestricted egress aids C2. Confidentiality and integrity are reduced, and the blast radius of a compromise grows. | N85: Default Security Group ({security_group.id}) rules allow traffic. | O85: Default Security Group ({security_group.id}) rules do not allow traffic. | P85: resource "aws_default_security_group" "<example_resource_name>" { vpc_id = "<example_vpc_id>" ingress = [] # Critical: removes all inbound rules from the default SG egress = [] # Critical: removes all outbound rules from the default SG } | R85: https://docs.aws.amazon.com/eks/latest/userguide/sec-group-reqs.html https://docs.aws.amazon.com/config/latest/developerguide/vpc-default-security-group-closed.html | S85: https://github.com/prowler-cloud/prowler/blob/master/prowler/providers/aws/services/ec2/ec2_securitygroup_default_restrict_traffic/ec2_securitygroup_default_restrict_traffic.py | T85: =IF(OR(L85="critical",AND(L85="high",OR(K85="IAM",K85="network"))),"T3",IF(OR(L85="high",L85="medium"),"T2","T1")) -> T3
A86: P-085 | B86: 6.6 | C86: Ensure routing tables for VPC peering are "least access" | D86: 6 Networking | E86: Level 2 | F86: Manual | G86: vpc_peering_routing_tables_with_least_privilege | H86: VPC peering connection route tables do not include 0.0.0.0/0 or entire requester/accepter VPC CIDR routes | I86: vpc | J86: AwsEc2VpcPeeringConnection | K86: network | L86: medium | M86: Broad peering routes expand cross-VPC reachability, enabling lateral movement and unauthorized discovery, harming confidentiality and integrity. Using 0.0.0.0/0 or full-CIDR paths also increases misrouting with overlapping ranges, reducing network availability. | N86: VPC Peering Connection {peer.id} does not comply with least privilege access since it accepts whole VPCs CIDR in its route tables. | O86: VPC Peering Connection {peer.id} comply with least privilege access. | P86: # Restrict VPC peering route to a specific subnet (least privilege) resource "aws_route" "peering_specific" { route_table_id = "<example_resource_id>" destination_cidr_block = "10.0.1.0/24" # CRITICAL: specific subnet, not 0.0.0.0/0 or full VPC CIDR vpc_peering_connection_id = "<example_resource_id>" } | R86: https://docs.aws.amazon.com/vpc/latest/peering/peering-configurations-partial-access.html | S86: https://github.com/prowler-cloud/prowler/blob/master/prowler/providers/aws/services/vpc/vpc_peering_routing_tables_with_least_privilege/vpc_peering_routing_tables_with_least_privilege.py | T86: =IF(OR(L86="critical",AND(L86="high",OR(K86="IAM",K86="network"))),"T3",IF(OR(L86="high",L86="medium"),"T2","T1")) -> T2
A87: P-086 | B87: 6.7 | C87: Ensure that the EC2 Metadata Service only allows IMDSv2 | D87: 6 Networking | E87: Level 1 | F87: Automated | G87: ec2_instance_imdsv2_enabled | H87: EC2 instance requires IMDSv2 or has the instance metadata service disabled | I87: ec2 | J87: AwsEc2Instance | K87: compute | L87: high | M87: Permitting IMDSv1 or optional tokens lets SSRF or compromised workloads retrieve temporary IAM credentials, impacting confidentiality and integrity. Stolen role creds can drive privilege escalation, unauthorized data access, and lateral movement across AWS resources. | N87: EC2 Instance {instance.id} has IMDSv2 disabled or not required. | O87: EC2 Instance {instance.id} has IMDSv2 enabled and required. | P87: # Enforce IMDSv2 on an EC2 instance resource "aws_instance" "<example_resource_name>" { ami = "<example_resource_id>" instance_type = "<example_resource_name>" metadata_options { http_tokens = "required" # Critical: Require IMDSv2 tokens (blocks IMDSv1) } } | Q87: aws ec2 modify-instance-metadata-options --instance-id <instance-id> --http-tokens required --http-endpoint enabled | R87: https://docs.aws.amazon.com/AWSEC2/latest/UserGuide/configuring-instance-metadata-service.html#configuring-instance-metadata-options | S87: https://github.com/prowler-cloud/prowler/blob/master/prowler/providers/aws/services/ec2/ec2_instance_imdsv2_enabled/ec2_instance_imdsv2_enabled.py | T87: =IF(OR(L87="critical",AND(L87="high",OR(K87="IAM",K87="network"))),"T3",IF(OR(L87="high",L87="medium"),"T2","T1")) -> T2

Sheet Edge_Cases
A1: Edge_ID | B1: Edge_Type | C1: CIS_ID | D1: Recommendation / Check | E1: What the real data shows | F1: Expected generator behaviour
A2: E-001 | B2: Manual assessment in CIS but partly automatable | C2: 2.1.1 | D2: Ensure centralized root access in AWS Organizations | E2: CIS marks this Manual; Prowler still automates part of it. | F2: Rule may ship but finding text must say it is a partial/automated proxy; SME sign-off required.
A3: E-002 | B3: No automated check exists | C3: 2.1.2 | D3: Ensure authorization guardrails for all AWS Organization accounts | E3: Prowler maps no check to this recommendation. | F3: Generator must NOT invent a rule. Expected output: 'manual control / organisational process', route to SME.
A4: E-003 | B4: No automated check exists | C4: 2.1.3 | D4: Ensure Organizations management account is not used for workloads | E4: Prowler maps no check to this recommendation. | F4: Generator must NOT invent a rule. Expected output: 'manual control / organisational process', route to SME.
A5: E-004 | B5: No automated check exists | C5: 2.1.4 | D5: Ensure Organizational Units are structured by environment and sensitivity | E5: Prowler maps no check to this recommendation. | F5: Generator must NOT invent a rule. Expected output: 'manual control / organisational process', route to SME.
A6: E-005 | B6: Manual assessment in CIS but partly automatable | C6: 2.1.5 | D6: Ensure delegated admin manages AWS Organizations policies | E6: CIS marks this Manual; Prowler still automates part of it. | F6: Rule may ship but finding text must say it is a partial/automated proxy; SME sign-off required.
A7: E-006 | B7: Manual assessment in CIS but partly automatable | C7: 2.1.6 | D7: Ensure delegated admins manage AWS Organizations-integrated services | E7: CIS marks this Manual; Prowler still automates part of it. | F7: Rule may ship but finding text must say it is a partial/automated proxy; SME sign-off required.
A8: E-007 | B8: Manual assessment in CIS but partly automatable | C8: 2.2 | D8: Maintain current AWS account contact details | E8: CIS marks this Manual; Prowler still automates part of it. | F8: Rule may ship but finding text must say it is a partial/automated proxy; SME sign-off required.
A9: E-008 | B9: Manual assessment in CIS but partly automatable | C9: 2.3 | D9: Ensure security contact information is registered | E9: CIS marks this Manual; Prowler still automates part of it. | F9: Rule may ship but finding text must say it is a partial/automated proxy; SME sign-off required.
A10: E-009 | B10: Manual assessment in CIS but partly automatable | C10: 2.6 | D10: Ensure hardware MFA is enabled for the 'root' user account | E10: CIS marks this Manual; Prowler still automates part of it. | F10: Rule may ship but finding text must say it is a partial/automated proxy; SME sign-off required.
A11: E-010 | B11: Manual assessment in CIS but partly automatable | C11: 2.7 | D11: Eliminate use of the 'root' user for administrative and daily tasks | E11: CIS marks this Manual; Prowler still automates part of it. | F11: Rule may ship but finding text must say it is a partial/automated proxy; SME sign-off required.
A12: E-011 | B12: One recommendation -> many rules | C12: 2.11 | D12: Ensure credentials unused for 45 days or more are disabled | E12: Reference checks: iam_user_accesskey_unused, iam_user_console_access_unused | F12: Generator must produce 2 rules (one per resource type/condition), not one combined rule.
... A52: E-051 | B52: IPv4 vs IPv6 variant | C52: 6.3 / 6.4 | D52: Security groups ingress from 0.0.0.0/0 and ::/0 | E52: Two CIS recommendations differ only by address family; same reference checks. | F52: Rule must cover both 0.0.0.0/0 and ::/0. Missing ::/0 = FALSE NEGATIVE.

Sheet Triage_Set
A1: Triage_ID | B1: Date | C1: AWS Announcement (title) | D1: URL | E1: Expected_Label | F1: Expected_Needs_Rule (Y/N) | G1: Label_Rationale | H1: Label_Status | I1: Predicted_Needs_Rule (Y/N) [INPUT] | J1: Correct?
A2: T-001 | B2: 26 Oct 2026 | C2: OpenAI GPT-6.1 Terra is now generally available on Amazon Bedrock | D2: https://aws.amazon.com/about-aws/whats-new/2026/10/openai-gpt-6-1-terra-on-amazon-bedrock/ | E2: No rule: AI/ML feature | F2: N | G2: AI/ML model or feature availability; no security setting announced. | H2: Draft (Claude): verify | J2: =IF(I2="","",IF(I2=F2,1,0))
A3: T-002 | B3: 26 Oct 2026 | C3: Amazon WorkSpaces Core Managed Instances now supports ModifyVolume API | D3: https://aws.amazon.com/about-aws/whats-new/2026/10/amazon-workspaces-cmi-modifyvolume/ | E3: No rule: non-security feature | F3: N | G3: Functional feature; no security-relevant configuration in title. | H3: Draft (Claude): verify | J3: =IF(I3="","",IF(I3=F3,1,0))
A4: T-003 | B4: 26 Oct 2026 | C4: Amazon SageMaker Unified Studio adds light mode support for IDC-based domains | D4: https://aws.amazon.com/about-aws/whats-new/2026/10/smus-light-mode | E4: No rule: AI/ML feature | F4: N | G4: AI/ML model or feature availability; no security setting announced. | H4: Draft (Claude): verify | J4: =IF(I4="","",IF(I4=F4,1,0))
A5: T-004 | B5: 26 Oct 2026 | C5: Amazon Connect Customer expands testing and simulation to validate flow action outcomes | D5: https://aws.amazon.com/about-aws/whats-new/2026/10/connect-customer-validate-flow-actions/ | E5: No rule: non-security feature | F5: N | G5: Functional feature; no security-relevant configuration in title. | H5: Draft (Claude): verify | J5: =IF(I5="","",IF(I5=F5,1,0))
A6: T-005 | B6: 26 Oct 2026 | C6: Amazon Connect Customer now lets you view metrics by customer lifetime value and repeat-caller status | D6: https://aws.amazon.com/about-aws/whats-new/2026/10/connect-customer-boma-segment/ | E6: No rule: non-security feature | F6: N | G6: Functional feature; no security-relevant configuration in title. | H6: Draft (Claude): verify | J6: =IF(I6="","",IF(I6=F6,1,0))
A7: T-006 | B7: 26 Oct 2026 | C7: Amazon Connect Customer now measures the outcomes that drive retention and revenue | D7: https://aws.amazon.com/about-aws/whats-new/2026/10/connect-customer-boma-metrics/ | E7: No rule: non-security feature | F7: N | G7: Functional feature; no security-relevant configuration in title. | H7: Draft (Claude): verify | J7: =IF(I7="","",IF(I7=F7,1,0))
A8: T-007 | B8: 26 Oct 2026 | C8: AWS IAM Identity Center now supports cross-Region trusted identity propagation | D8: https://aws.amazon.com/about-aws/whats-new/2026/10/aws-iam-identity-center-cross-region-tip/ | E8: New rule candidate | F8: Y | G8: New identity-propagation setting; check trust scope configuration. | H8: Draft (Claude): verify | J8: =IF(I8="","",IF(I8=F8,1,0))
A9: T-008 | B9: 26 Oct 2026 | C9: AWS Key Management Service now supports ML-KEM for post-quantum key encapsulation | D9: https://aws.amazon.com/about-aws/whats-new/2026/10/kms-ml-kem-post-quantum/ | E9: New rule candidate | F9: Y | G9: New KMS key spec; possible rule on post-quantum readiness / key spec policy. | H9: Draft (Claude): verify | J9: =IF(I9="","",IF(I9=F9,1,0))
A10: T-009 | B10: 26 Oct 2026 | C10: AWS EC2 Auto Scaling now supports Launch Before Terminate at account-level to replace instances | D10: https://aws.amazon.com/about-aws/whats-new/2026/10/ec2-auto-scaling-launch-before-terminate/ | E10: No rule: non-security feature | F10: N | G10: Functional feature; no security-relevant configuration in title. | H10: Draft (Claude): verify | J10: =IF(I10="","",IF(I10=F10,1,0))
A11: T-010 | B11: 26 Oct 2026 | C11: Amazon RDS now supports the latest Cumulative Update and GDR updates for Microsoft SQL Server | D11: https://aws.amazon.com/about-aws/whats-new/2026/10/amazon-rds-supports-latest-cumulative-update-gdr-microsoft-sql-server/ | E11: No rule: non-security feature | F11: N | G11: Functional feature; no security-relevant configuration in title. | H11: Draft (Claude): verify | J11: =IF(I11="","",IF(I11=F11,1,0))
A12: T-011 | B12: 26 Oct 2026 | C12: AWS Glue Data Catalog now supports OAuth for Apache Iceberg REST Catalog APIs | D12: https://aws.amazon.com/about-aws/whats-new/2026/10/glue-catalog-oauth-iceberg-rest/ | E12: New rule candidate | F12: Y | G12: New auth option on catalog API; check authentication configuration. | H12: Draft (Claude): verify | J12: =IF(I12="","",IF(I12=F12,1,0))
A13: T-012 | B13: 23 Oct 2026 | C13: Web Search on Amazon Bedrock now supports domain filtering and user location controls | D13: https://aws.amazon.com/about-aws/whats-new/2026/10/bedrock-web-search-domain-user-location/ | E13: No rule: AI/ML feature | F13: N | G13: AI/ML model or feature availability; no security setting announced. | H13: Draft (Claude): verify | J13: =IF(I13="","",IF(I13=F13,1,0))
... A101: T-100 | B101: 14 Oct 2026 | C101: AWS Lambda recursive loop detection now supports Amazon EventBridge Custom event buses | D101: https://aws.amazon.com/about-aws/whats-new/2026/10/lambda-recursive-loops-eventbridge-custom | E101: No rule: non-security feature | F101: N | G101: Functional feature; no security-relevant configuration in title. | H101: Draft (Claude): verify | J101: =IF(I101="","",IF(I101=F101,1,0))

Sheet Version_Drift
A1: Drift_ID | B1: Change_Type | C1: CIS v6.0 ID | D1: CIS v6.0 Title | E1: CIS v7.0 ID | F1: CIS v7.0 Title | G1: Reference checks | H1: Expected maintenance action
A2: V-001 | B2: Reworded / renumbered | C2: 2.1 | D2: Maintain current contact details | E2: 2.2 | F2: Maintain current AWS account contact details | G2: account_maintain_current_contact_details | H2: Keep rule; update CIS ID and title in rule metadata and on customer findings.
A3: V-002 | B3: Removed in v7.0 | C3: 2.10 | D3: Do not create access keys during initial setup for IAM users with a console password | G3: iam_user_no_setup_initial_access_key | H3: Do not delete rule automatically; re-map to other frameworks or mark 'not in CIS v7.0'. SME decision.
A4: V-003 | B4: Removed in v7.0 | C4: 2.12 | D4: Ensure there is only one active access key for any single IAM user | G4: iam_user_two_active_access_key | H4: Do not delete rule automatically; re-map to other frameworks or mark 'not in CIS v7.0'. SME decision.
A5: V-004 | B5: Reworded / renumbered | C5: 2.15 | D5: Ensure IAM policies that allow full *:* administrative privileges are not attached | E5: 2.14 | F5: Ensure IAM policies that allow full "*:*" administrative privileges are not attached | G5: iam_aws_attached_policy_no_administrative_privileges, iam_customer_attached_policy_no_administrative_privileges | H5: Keep rule; update CIS ID and title in rule metadata and on customer findings.
A6: V-005 | B6: Reworded / renumbered | C6: 6.6 | D6: Ensure routing tables for VPC peering are least access | E6: 6.6 | F6: Ensure routing tables for VPC peering are "least access" | G6: vpc_peering_routing_tables_with_least_privilege | H6: Keep rule; update CIS ID and title in rule metadata and on customer findings.
A7: V-006 | B7: Added in v7.0 | E7: 2.1.1 | F7: Ensure centralized root access in AWS Organizations | G7: iam_root_credentials_management_enabled | H7: Map existing rule(s) to new recommendation.
A8: V-007 | B8: Added in v7.0 | E8: 2.1.2 | F8: Ensure authorization guardrails for all AWS Organization accounts | H8: No reference check exists: candidate for NEW rule or manual control.
A9: V-008 | B9: Added in v7.0 | E9: 2.1.3 | F9: Ensure Organizations management account is not used for workloads | H9: No reference check exists: candidate for NEW rule or manual control.
A10: V-009 | B10: Added in v7.0 | E10: 2.1.4 | F10: Ensure Organizational Units are structured by environment and sensitivity | H10: No reference check exists: candidate for NEW rule or manual control.
A11: V-010 | B11: Added in v7.0 | E11: 2.1.5 | F11: Ensure delegated admin manages AWS Organizations policies | G11: organizations_delegated_administrators | H11: Map existing rule(s) to new recommendation.
A12: V-011 | B12: Added in v7.0 | E12: 2.1.6 | F12: Ensure delegated admins manage AWS Organizations-integrated services | G12: organizations_delegated_administrators | H12: Map existing rule(s) to new recommendation.
A13: V-012 | B13: Added in v7.0 | E13: 2.21 | F13: Ensure AWS resource policies do not allow unrestricted access using 'Principal': '*' | G13: s3_bucket_policy_public_write_access, sqs_queues_not_publicly_accessible, sns_topics_not_publicly_accessible, awslambda_function_not_publicly_accessible, kms_key_not_publicly_accessible, glacier_vaults_policy_public_access, secretsmanager_not_publicly_accessible, eventbridge_bus_exposed | H13: Map existing rule(s) to new recommendation.
A14: V-013 | B14: Added in v7.0 | E14: 4.10 | F14: Ensure all AWS-managed web front-end services have access logging enabled | G14: cloudfront_distributions_logging_enabled, elbv2_logging_enabled, apigateway_restapi_logging_enabled, apigatewayv2_api_access_logging_enabled | H14: Map existing rule(s) to new recommendation.
A15: V-014 | B15: Added in v7.0 | E15: 6.8 | F15: Ensure VPC Endpoints are used for access to AWS Services | H15: No reference check exists: candidate for NEW rule or manual control.
A16: V-015 | B16: Renumbered | C16: 2.2 | D16: Ensure security contact information is registered | E16: 2.3 | F16: Ensure security contact information is registered | G16: account_security_contact_information_is_registered | H16: Update CIS ID in rule metadata.
A17: V-016 | B17: Renumbered | C17: 2.3 | D17: Ensure no 'root' user account access key exists | E17: 2.4 | F17: Ensure no 'root' user account access key exists | G17: iam_no_root_access_key | H17: Update CIS ID in rule metadata.
A18: V-017 | B18: Renumbered | C18: 2.4 | D18: Ensure MFA is enabled for the 'root' user account | E18: 2.5 | F18: Ensure MFA is enabled for the 'root' user account | G18: iam_root_mfa_enabled | H18: Update CIS ID in rule metadata.
A19: V-018 | B19: Renumbered | C19: 2.5 | D19: Ensure hardware MFA is enabled for the 'root' user account | E19: 2.6 | F19: Ensure hardware MFA is enabled for the 'root' user account | G19: iam_root_hardware_mfa_enabled | H19: Update CIS ID in rule metadata.
A20: V-019 | B20: Renumbered | C20: 2.6 | D20: Eliminate use of the 'root' user for administrative and daily tasks | E20: 2.7 | F20: Eliminate use of the 'root' user for administrative and daily tasks | G20: iam_avoid_root_usage | H20: Update CIS ID in rule metadata.
A21: V-020 | B21: Renumbered | C21: 2.7 | D21: Ensure IAM password policy requires minimum length of 14 or greater | E21: 2.8 | F21: Ensure IAM password policy requires minimum length of 14 or greater | G21: iam_password_policy_minimum_length_14 | H21: Update CIS ID in rule metadata.
A22: V-021 | B22: Renumbered | C22: 2.8 | D22: Ensure IAM password policy prevents password reuse | E22: 2.9 | F22: Ensure IAM password policy prevents password reuse | G22: iam_password_policy_reuse_24 | H22: Update CIS ID in rule metadata.
A23: V-022 | B23: Renumbered | C23: 2.9 | D23: Ensure multi-factor authentication (MFA) is enabled for all IAM users that have a console password | E23: 2.10 | F23: Ensure multi-factor authentication (MFA) is enabled for all IAM users that have a console password | G23: iam_user_mfa_enabled_console_access | H23: Update CIS ID in rule metadata.
A24: V-023 | B24: Renumbered | C24: 2.13 | D24: Ensure access keys are rotated every 90 days or less | E24: 2.12 | F24: Ensure access keys are rotated every 90 days or less | G24: iam_rotate_access_key_90_days | H24: Update CIS ID in rule metadata.
A25: V-024 | B25: Renumbered | C25: 2.14 | D25: Ensure IAM users receive permissions only through groups | E25: 2.13 | F25: Ensure IAM users receive permissions only through groups | G25: iam_policy_attached_only_to_group_or_roles | H25: Update CIS ID in rule metadata.
A26: V-025 | B26: Renumbered | C26: 2.16 | D26: Ensure a support role has been created to manage incidents with AWS Support | E26: 2.15 | F26: Ensure a support role has been created to manage incidents with AWS Support | G26: iam_support_role_created | H26: Update CIS ID in rule metadata.
A27: V-026 | B27: Renumbered | C27: 2.17 | D27: Ensure IAM instance roles are used for AWS resource access from instances | E27: 2.16 | F27: Ensure IAM instance roles are used for AWS resource access from instances | G27: ec2_instance_profile_attached | H27: Update CIS ID in rule metadata.
... A32: V-031 | B32: Check mapping changed | C32: 6.1.1 | D32: Ensure EBS volume encryption is enabled in all regions | E32: 6.1.1 | F32: Ensure EBS volume encryption is enabled in all regions | G32: v6: ec2_ebs_volume_encryption | v7: ec2_ebs_default_encryption | H32: Re-map rules to recommendation; verify coverage.

Sheet Eval_Scorecard
A1: Eval Scorecard: fill the yellow cells after running your pipeline on each golden row
A2: Legend: yellow = your input (1 = yes / correct, 0 = no). Expected values are pulled from Positive_Set by formula. Example of a filled row: P-001 | Severity predicted 'medium' | Citation 1 | Logic 1 | Compliant test passes 1 | Non-compliant test fails 1.
A4: GS_ID | B4: Expected_Check_ID | C4: Expected_Severity | D4: Predicted_Severity [INPUT] | E4: Severity_Match | F4: Citation_Correct (1/0) [INPUT] | G4: Logic_Equivalent (1/0) [INPUT] | H4: Compliant_Fixture_PASS (1/0) [INPUT] | I4: NonCompliant_Fixture_FAIL (1/0) [INPUT] | J4: Rule_Correct (all gates) | K4: SME_Review_Minutes [INPUT] | M4: SUMMARY (Positive_Set)
A5: =Positive_Set!A2 -> P-001 | B5: =INDEX(Positive_Set!$G$2:$G$87,MATCH(A5,Positive_Set!$A$2:$A$87,0)) -> iam_root_credentials_management_enabled | C5: =INDEX(Positive_Set!$L$2:$L$87,MATCH(A5,Positive_Set!$A$2:$A$87,0)) -> high | E5: =IF(D5="","",IF(LOWER(D5)=C5,1,0)) | J5: =IF(COUNT(F5:I5)<4,"",IF(AND(E5=1,F5=1,G5=1,H5=1,I5=1),1,0)) | M5: Rows in golden set | N5: =COUNTA(A5:A90) -> 86
A6: =Positive_Set!A3 -> P-002 | B6: =INDEX(Positive_Set!$G$2:$G$87,MATCH(A6,Positive_Set!$A$2:$A$87,0)) -> organizations_delegated_administrators | C6: =INDEX(Positive_Set!$L$2:$L$87,MATCH(A6,Positive_Set!$A$2:$A$87,0)) -> critical | E6: =IF(D6="","",IF(LOWER(D6)=C6,1,0)) | J6: =IF(COUNT(F6:I6)<4,"",IF(AND(E6=1,F6=1,G6=1,H6=1,I6=1),1,0)) | M6: Rows scored | N6: =COUNT(J5:J90) -> 0
A7: =Positive_Set!A4 -> P-003 | B7: =INDEX(Positive_Set!$G$2:$G$87,MATCH(A7,Positive_Set!$A$2:$A$87,0)) -> organizations_delegated_administrators | C7: =INDEX(Positive_Set!$L$2:$L$87,MATCH(A7,Positive_Set!$A$2:$A$87,0)) -> critical | E7: =IF(D7="","",IF(LOWER(D7)=C7,1,0)) | J7: =IF(COUNT(F7:I7)<4,"",IF(AND(E7=1,F7=1,G7=1,H7=1,I7=1),1,0)) | M7: Rule accuracy (all gates passed) | N7: =IFERROR(SUM(J5:J90)/COUNT(J5:J90),"")
A8: =Positive_Set!A5 -> P-004 | B8: =INDEX(Positive_Set!$G$2:$G$87,MATCH(A8,Positive_Set!$A$2:$A$87,0)) -> account_maintain_current_contact_details | C8: =INDEX(Positive_Set!$L$2:$L$87,MATCH(A8,Positive_Set!$A$2:$A$87,0)) -> medium | E8: =IF(D8="","",IF(LOWER(D8)=C8,1,0)) | J8: =IF(COUNT(F8:I8)<4,"",IF(AND(E8=1,F8=1,G8=1,H8=1,I8=1),1,0)) | M8: Severity accuracy | N8: =IFERROR(SUM(E5:E90)/COUNT(E5:E90),"")
A9: =Positive_Set!A6 -> P-005 | B9: =INDEX(Positive_Set!$G$2:$G$87,MATCH(A9,Positive_Set!$A$2:$A$87,0)) -> account_security_contact_information_is_registered | C9: =INDEX(Positive_Set!$L$2:$L$87,MATCH(A9,Positive_Set!$A$2:$A$87,0)) -> medium | E9: =IF(D9="","",IF(LOWER(D9)=C9,1,0)) | J9: =IF(COUNT(F9:I9)<4,"",IF(AND(E9=1,F9=1,G9=1,H9=1,I9=1),1,0)) | M9: Citation accuracy (target 100%) | N9: =IFERROR(SUM(F5:F90)/COUNT(F5:F90),"")
A10: =Positive_Set!A7 -> P-006 | B10: =INDEX(Positive_Set!$G$2:$G$87,MATCH(A10,Positive_Set!$A$2:$A$87,0)) -> iam_no_root_access_key | C10: =INDEX(Positive_Set!$L$2:$L$87,MATCH(A10,Positive_Set!$A$2:$A$87,0)) -> critical | E10: =IF(D10="","",IF(LOWER(D10)=C10,1,0)) | J10: =IF(COUNT(F10:I10)<4,"",IF(AND(E10=1,F10=1,G10=1,H10=1,I10=1),1,0)) | M10: Avg SME review minutes | N10: =IFERROR(AVERAGE(K5:K90),"")
A11: =Positive_Set!A8 -> P-007 | B11: =INDEX(Positive_Set!$G$2:$G$87,MATCH(A11,Positive_Set!$A$2:$A$87,0)) -> iam_root_mfa_enabled | C11: =INDEX(Positive_Set!$L$2:$L$87,MATCH(A11,Positive_Set!$A$2:$A$87,0)) -> critical | E11: =IF(D11="","",IF(LOWER(D11)=C11,1,0)) | J11: =IF(COUNT(F11:I11)<4,"",IF(AND(E11=1,F11=1,G11=1,H11=1,I11=1),1,0))
A12: =Positive_Set!A9 -> P-008 | B12: =INDEX(Positive_Set!$G$2:$G$87,MATCH(A12,Positive_Set!$A$2:$A$87,0)) -> iam_root_hardware_mfa_enabled | C12: =INDEX(Positive_Set!$L$2:$L$87,MATCH(A12,Positive_Set!$A$2:$A$87,0)) -> critical | E12: =IF(D12="","",IF(LOWER(D12)=C12,1,0)) | J12: =IF(COUNT(F12:I12)<4,"",IF(AND(E12=1,F12=1,G12=1,H12=1,I12=1),1,0)) | M12: SUMMARY (Triage_Set: 'needs rule' class)
A13: =Positive_Set!A10 -> P-009 | B13: =INDEX(Positive_Set!$G$2:$G$87,MATCH(A13,Positive_Set!$A$2:$A$87,0)) -> iam_avoid_root_usage | C13: =INDEX(Positive_Set!$L$2:$L$87,MATCH(A13,Positive_Set!$A$2:$A$87,0)) -> high | E13: =IF(D13="","",IF(LOWER(D13)=C13,1,0)) | J13: =IF(COUNT(F13:I13)<4,"",IF(AND(E13=1,F13=1,G13=1,H13=1,I13=1),1,0)) | M13: True positives | N13: =COUNTIFS(Triage_Set!F2:F101,"Y",Triage_Set!I2:I101,"Y") -> 0
A14: =Positive_Set!A11 -> P-010 | B14: =INDEX(Positive_Set!$G$2:$G$87,MATCH(A14,Positive_Set!$A$2:$A$87,0)) -> iam_password_policy_minimum_length_14 | C14: =INDEX(Positive_Set!$L$2:$L$87,MATCH(A14,Positive_Set!$A$2:$A$87,0)) -> medium | E14: =IF(D14="","",IF(LOWER(D14)=C14,1,0)) | J14: =IF(COUNT(F14:I14)<4,"",IF(AND(E14=1,F14=1,G14=1,H14=1,I14=1),1,0)) | M14: False positives | N14: =COUNTIFS(Triage_Set!F2:F101,"N",Triage_Set!I2:I101,"Y") -> 0
A15: =Positive_Set!A12 -> P-011 | B15: =INDEX(Positive_Set!$G$2:$G$87,MATCH(A15,Positive_Set!$A$2:$A$87,0)) -> iam_password_policy_reuse_24 | C15: =INDEX(Positive_Set!$L$2:$L$87,MATCH(A15,Positive_Set!$A$2:$A$87,0)) -> medium | E15: =IF(D15="","",IF(LOWER(D15)=C15,1,0)) | J15: =IF(COUNT(F15:I15)<4,"",IF(AND(E15=1,F15=1,G15=1,H15=1,I15=1),1,0)) | M15: False negatives | N15: =COUNTIFS(Triage_Set!F2:F101,"Y",Triage_Set!I2:I101,"N") -> 0
A16: =Positive_Set!A13 -> P-012 | B16: =INDEX(Positive_Set!$G$2:$G$87,MATCH(A16,Positive_Set!$A$2:$A$87,0)) -> iam_user_mfa_enabled_console_access | C16: =INDEX(Positive_Set!$L$2:$L$87,MATCH(A16,Positive_Set!$A$2:$A$87,0)) -> high | E16: =IF(D16="","",IF(LOWER(D16)=C16,1,0)) | J16: =IF(COUNT(F16:I16)<4,"",IF(AND(E16=1,F16=1,G16=1,H16=1,I16=1),1,0)) | M16: Precision | N16: =IFERROR(N13/(N13+N14),"")
A17: =Positive_Set!A14 -> P-013 | B17: =INDEX(Positive_Set!$G$2:$G$87,MATCH(A17,Positive_Set!$A$2:$A$87,0)) -> iam_user_accesskey_unused | C17: =INDEX(Positive_Set!$L$2:$L$87,MATCH(A17,Positive_Set!$A$2:$A$87,0)) -> medium | E17: =IF(D17="","",IF(LOWER(D17)=C17,1,0)) | J17: =IF(COUNT(F17:I17)<4,"",IF(AND(E17=1,F17=1,G17=1,H17=1,I17=1),1,0)) | M17: Recall | N17: =IFERROR(N13/(N13+N15),"")
A18: =Positive_Set!A15 -> P-014 | B18: =INDEX(Positive_Set!$G$2:$G$87,MATCH(A18,Positive_Set!$A$2:$A$87,0)) -> iam_user_console_access_unused | C18: =INDEX(Positive_Set!$L$2:$L$87,MATCH(A18,Positive_Set!$A$2:$A$87,0)) -> medium | E18: =IF(D18="","",IF(LOWER(D18)=C18,1,0)) | J18: =IF(COUNT(F18:I18)<4,"",IF(AND(E18=1,F18=1,G18=1,H18=1,I18=1),1,0))
A19: =Positive_Set!A16 -> P-015 | B19: =INDEX(Positive_Set!$G$2:$G$87,MATCH(A19,Positive_Set!$A$2:$A$87,0)) -> iam_rotate_access_key_90_days | C19: =INDEX(Positive_Set!$L$2:$L$87,MATCH(A19,Positive_Set!$A$2:$A$87,0)) -> medium | E19: =IF(D19="","",IF(LOWER(D19)=C19,1,0)) | J19: =IF(COUNT(F19:I19)<4,"",IF(AND(E19=1,F19=1,G19=1,H19=1,I19=1),1,0))
A20: =Positive_Set!A17 -> P-016 | B20: =INDEX(Positive_Set!$G$2:$G$87,MATCH(A20,Positive_Set!$A$2:$A$87,0)) -> iam_policy_attached_only_to_group_or_roles | C20: =INDEX(Positive_Set!$L$2:$L$87,MATCH(A20,Positive_Set!$A$2:$A$87,0)) -> low | E20: =IF(D20="","",IF(LOWER(D20)=C20,1,0)) | J20: =IF(COUNT(F20:I20)<4,"",IF(AND(E20=1,F20=1,G20=1,H20=1,I20=1),1,0))
A21: =Positive_Set!A18 -> P-017 | B21: =INDEX(Positive_Set!$G$2:$G$87,MATCH(A21,Positive_Set!$A$2:$A$87,0)) -> iam_aws_attached_policy_no_administrative_privileges | C21: =INDEX(Positive_Set!$L$2:$L$87,MATCH(A21,Positive_Set!$A$2:$A$87,0)) -> critical | E21: =IF(D21="","",IF(LOWER(D21)=C21,1,0)) | J21: =IF(COUNT(F21:I21)<4,"",IF(AND(E21=1,F21=1,G21=1,H21=1,I21=1),1,0))
A22: =Positive_Set!A19 -> P-018 | B22: =INDEX(Positive_Set!$G$2:$G$87,MATCH(A22,Positive_Set!$A$2:$A$87,0)) -> iam_customer_attached_policy_no_administrative_privileges | C22: =INDEX(Positive_Set!$L$2:$L$87,MATCH(A22,Positive_Set!$A$2:$A$87,0)) -> high | E22: =IF(D22="","",IF(LOWER(D22)=C22,1,0)) | J22: =IF(COUNT(F22:I22)<4,"",IF(AND(E22=1,F22=1,G22=1,H22=1,I22=1),1,0))
A23: =Positive_Set!A20 -> P-019 | B23: =INDEX(Positive_Set!$G$2:$G$87,MATCH(A23,Positive_Set!$A$2:$A$87,0)) -> iam_support_role_created | C23: =INDEX(Positive_Set!$L$2:$L$87,MATCH(A23,Positive_Set!$A$2:$A$87,0)) -> low | E23: =IF(D23="","",IF(LOWER(D23)=C23,1,0)) | J23: =IF(COUNT(F23:I23)<4,"",IF(AND(E23=1,F23=1,G23=1,H23=1,I23=1),1,0))
A24: =Positive_Set!A21 -> P-020 | B24: =INDEX(Positive_Set!$G$2:$G$87,MATCH(A24,Positive_Set!$A$2:$A$87,0)) -> ec2_instance_profile_attached | C24: =INDEX(Positive_Set!$L$2:$L$87,MATCH(A24,Positive_Set!$A$2:$A$87,0)) -> medium | E24: =IF(D24="","",IF(LOWER(D24)=C24,1,0)) | J24: =IF(COUNT(F24:I24)<4,"",IF(AND(E24=1,F24=1,G24=1,H24=1,I24=1),1,0))
A25: =Positive_Set!A22 -> P-021 | B25: =INDEX(Positive_Set!$G$2:$G$87,MATCH(A25,Positive_Set!$A$2:$A$87,0)) -> iam_no_expired_server_certificates_stored | C25: =INDEX(Positive_Set!$L$2:$L$87,MATCH(A25,Positive_Set!$A$2:$A$87,0)) -> high | E25: =IF(D25="","",IF(LOWER(D25)=C25,1,0)) | J25: =IF(COUNT(F25:I25)<4,"",IF(AND(E25=1,F25=1,G25=1,H25=1,I25=1),1,0))
A26: =Positive_Set!A23 -> P-022 | B26: =INDEX(Positive_Set!$G$2:$G$87,MATCH(A26,Positive_Set!$A$2:$A$87,0)) -> accessanalyzer_enabled | C26: =INDEX(Positive_Set!$L$2:$L$87,MATCH(A26,Positive_Set!$A$2:$A$87,0)) -> low | E26: =IF(D26="","",IF(LOWER(D26)=C26,1,0)) | J26: =IF(COUNT(F26:I26)<4,"",IF(AND(E26=1,F26=1,G26=1,H26=1,I26=1),1,0))
A27: =Positive_Set!A24 -> P-023 | B27: =INDEX(Positive_Set!$G$2:$G$87,MATCH(A27,Positive_Set!$A$2:$A$87,0)) -> iam_check_saml_providers_sts | C27: =INDEX(Positive_Set!$L$2:$L$87,MATCH(A27,Positive_Set!$A$2:$A$87,0)) -> low | E27: =IF(D27="","",IF(LOWER(D27)=C27,1,0)) | J27: =IF(COUNT(F27:I27)<4,"",IF(AND(E27=1,F27=1,G27=1,H27=1,I27=1),1,0))
A28: =Positive_Set!A25 -> P-024 | B28: =INDEX(Positive_Set!$G$2:$G$87,MATCH(A28,Positive_Set!$A$2:$A$87,0)) -> iam_policy_cloudshell_admin_not_attached | C28: =INDEX(Positive_Set!$L$2:$L$87,MATCH(A28,Positive_Set!$A$2:$A$87,0)) -> medium | E28: =IF(D28="","",IF(LOWER(D28)=C28,1,0)) | J28: =IF(COUNT(F28:I28)<4,"",IF(AND(E28=1,F28=1,G28=1,H28=1,I28=1),1,0))
A29: =Positive_Set!A26 -> P-025 | B29: =INDEX(Positive_Set!$G$2:$G$87,MATCH(A29,Positive_Set!$A$2:$A$87,0)) -> s3_bucket_policy_public_write_access | C29: =INDEX(Positive_Set!$L$2:$L$87,MATCH(A29,Positive_Set!$A$2:$A$87,0)) -> critical | E29: =IF(D29="","",IF(LOWER(D29)=C29,1,0)) | J29: =IF(COUNT(F29:I29)<4,"",IF(AND(E29=1,F29=1,G29=1,H29=1,I29=1),1,0))
... A90: =Positive_Set!A87 -> P-086 | B90: =INDEX(Positive_Set!$G$2:$G$87,MATCH(A90,Positive_Set!$A$2:$A$87,0)) -> ec2_instance_imdsv2_enabled | C90: =INDEX(Positive_Set!$L$2:$L$87,MATCH(A90,Positive_Set!$A$2:$A$87,0)) -> high | E90: =IF(D90="","",IF(LOWER(D90)=C90,1,0)) | J90: =IF(COUNT(F90:I90)<4,"",IF(AND(E90=1,F90=1,G90=1,H90=1,I90=1),1,0))

Sheet Sources
A1: Source | B1: URL
A2: Prowler CIS v7.0 AWS mapping | B2: https://github.com/prowler-cloud/prowler/blob/master/prowler/compliance/aws/cis_7.0_aws.json
A3: Prowler CIS v6.0 AWS mapping | B3: https://github.com/prowler-cloud/prowler/blob/master/prowler/compliance/aws/cis_6.0_aws.json
A4: Prowler AWS checks (metadata + code) | B4: https://github.com/prowler-cloud/prowler/tree/master/prowler/providers/aws/services
A5: Prowler licence (Apache-2.0) | B5: https://github.com/prowler-cloud/prowler/blob/master/LICENSE
A6: CIS AWS Foundations Benchmark (free PDF download) | B6: https://www.cisecurity.org/benchmark/amazon_web_services
A7: CIS Benchmarks April 2026 update (v7.0.0 release) | B7: https://www.cisecurity.org/insights/blog/cis-benchmarks-april-2026-update
A8: AWS What's New RSS feed (retrieved 27 Oct 2026) | B8: https://aws.amazon.com/about-aws/whats-new/recent/feed/
